Workbook
Name _Hlk142582612: '172,280 Notices'!$A$22
Name _Hlk142582612: '183(3),179 Notices'!#REF!
Name _Hlk142582612: '212 Notice'!#REF!

Sheet Data Input
C3: Return's Data Input | H3: Circle Office Data
C4: Kiel© | D4: 2025-26 | E4: wUAvBGb | F4: 387493583464 | H4: Kg©KZ©vi bvgt | J4: Ki mv‡K©jt | K4: 16
C5: wiUvb© `vwL‡ji Zvst | D5: =DATE(2025,11,1) -> 45962 | E5: Ki wba©vi‡Yi Zvst | F5: =DATE(2026,12,30) -> 46386 | H5: c`ext | I5: উপ কর কমিশনার | J5: Ki AÂj | K5: খুলনা
C6: bvg | D6: Rbve †gvt bvCg nvmvb | H6: b¨~bZg Ki`vq | I6: 4000 | J6: †dvbt | K6: 02-2222244444
C7: wVKvbv | H7: mv‡K©‡ji wVKvbvt | I7: 50/1, wfAvBwc †ivW, bqvcëb, XvKv| | J7: I‡qemvBU/mvf©vi wjsKt | K7: https://tinyurl.com/easypeasytax
C8: aiY: | D8: পুরুষ | E8: Ki`vZvi cÖK…wZ | F8: Individual | H8: mv‡K©j aiY | I8: আয়কর কোম্পানী ব্যতীত | J8: Ki AÂjwfwËK †KvW | K8: ='MisC Cal-1'!AF2 -> 1-1141-0055-0১১১
C9: wiUv‡b©i aiY * | D9: স্বনির্ধারণী | E9: Gross Receipt/Sales | F9: 70000000
C10: bxU m¤c`t * | D10: <= ৪ কোটি | E10: ='MisC Cal-2'!C13 -> cwi‡ek mviPvR© | F10: 0 | H10: Appeal Zone Input
C11: ='MisC Cal-2'!C5 -> 8000 et dzt evwo/GKvwaK Mvwo | D11: প্রযোজ্য নহে | E11: †emiKvwi PvKwi n‡Z Avq | F11: বেতন-ভাতা (Yes) | H11: Ki Avwcj AÂj : | I11: খুলনা | J11: Avwcj AwZwi³/ hyMœ Ki Kwgkbvi, †iÄ: | K11: 3
C13: Salary Data Input
D14: †emiKvwi PvKwi n‡Z Avq (‡eZb I fvZvw`) | E14: Av‡qi cwigvY | F14: Ki-Ae¨vnwZ cÖvß Avq | H14: Easy-Peasy Tax
D15: মূল বেতন/মজুরি/পারিশ্রমিক ইত্যাদি | E15: 1600000
D16: মোটরগাড়ি প্রতি সুবিধা
D17: বাড়ি ভাড়া ভাতা
D18: চিকিৎসা ভাতা/পারকুইজিট ইত্যাদি
D19: উৎসব/উৎসাহ বোনাস/অন্যান্য ইত্যাদি
D20: সম্পূর্ণ করযোগ্য ভাতা/ভাতা সমূহ
D21: আনুতোষিক/অ্যানুইটি, পেনশন বা ইহাদের সম্পূরক (করমুক্ত) | E21: 0 | F21: =E21 -> 0 | K21: Mr. Potter
D22: †gvU Avq = | E22: ='MisC Cal-1'!I94 -> 1600000 | F22: ='MisC Cal-1'!J94 -> 500000
C24: Income's Data | H24: Return's Output
D25: LvZ wfwËK Avq | E25: wbU Ki‡hvM¨ | F25: Dr‡m KwZ©Z Ki | H25: ='MisC Intrst-3'!N31 -> Tax Day | I25: ='MisC Intrst-3'!O31 -> ৩০ নভেম্বর | J25: Ki wba©viY el©t | K25: ='MisC Intrst-3'!L24 -> 0
D26: †emiKvwi PvKwi n‡Z Ki‡hvM¨ †gvU Avq | E26: ='MisC Cal-1'!K94 -> 1100000 | F26: 9000 | H26: 162 avivq my` nvi (%) | I26: ='MisC Intrst-3'!L9 -> 10 | J26: ='MisC Cal-1'!AK4 -> Trunover Tax | K26: =_xlfn.XLOOKUP(J26,'MisC Cal-1'!AM3:AM4,'MisC Cal-1'!AL3:AL4,0,1) -> Individual
D27: (সরকারি/সমমান) চাকরি হতে করযোগ্য আয় | E27: 0 | F27: 0
D28: পেশাগত আয় | E28: 3862355 | F28: 75000
D29: মূলধনী আয় (নিয়মিত করদায়ভুক্ত) | H29: Taxes & Charges
D30: অন্যান্য খাতের আয় | E30: 0
D31: ='MisC Cal-1'!B133 -> ব্যক্তিসংঘ/ফার্মের করারোপিত শেয়ার আয় | E31: 500000 | F31: 0 | J31: =F50&" avivbymv‡i bxU AvqKi " -> 82wewe/82wm (AvqKi Aa¨v‡`k, 1984)/183(7) avivbymv‡i bxU AvqKi | K31: ='Sheet of Calculation'!C51 -> 724431.84
D32: ='MisC Cal-1'!B134 -> ৫৬/৭৬(৬) ধারায় নিয়মিত করদায়ভুক্ত আয় | E32: 0 | H32: 160 Ges 162 avivq my` (‡hvM) | I32: ='MisC Intrst-3'!D18 -> 53835.202 | J32: dv‡g©i Rb¨ Ki Ae¨vnwZ | K32: ='MisC Cal-2'!D68 -> 110182.01
D33: wbqwgZ Drm n‡Z ‡gvU Avq (163 avivi Avq e¨wZZ) | E33: ='Sheet of Calculation'!D24 -> 5462355 | F33: ='Sheet of Calculation'!E24 -> 84000 | H33: 18(4) avivi mviPvR© (‡hvM) | I33: ='MisC Cal-2'!D10 -> 0 | J33: ‡gvU †iqvZ | K33: ='Sheet of Calculation'!F58 -> 258717.26
C34: Minimum Tax Data | H34: ='MisC Intrst-3'!T32&" wej¤^ my` (‡hvM)" -> wej¤^ my` (‡hvM) | I34: ='MisC Intrst-3'!L43 -> 0 | J34: cwi‡ek mviPvR© (‡hvM) | K34: ='MisC Cal-2'!D11 -> 0
D35: আর্থিক পরিসম্পদ হতে ১৬৩ ধারার আয় | E35: =932315+795827 -> 1728142 | F35: 180000 | H35: Rwigvbv ev Ab¨vb¨ †Kvb Ki`vq | I35: =F51+F53 -> 0 | J35: 214(4) avivq my`t | K35: =F52 -> 0
D36: ‡gvU Avq (163 avivi b¨~bZg Ki`vqfz³ Avq mn) | E36: ='Sheet of Calculation'!D26 -> 7190497 | F36: =F33+F35 -> 264000 | I36: ='Sheet of Calculation'!E52 -> cÖ‡`q AvqKi | J36: ='Sheet of Calculation'!F52 -> 598267.04 | K36: =ROUND(J36,0) -> 598267
D37: * 163 avivi P‚ovšÍ Ki`vq Avq (mÂqc‡Îi gybvdv, BZ¨vw`) | E37: 0 | F37: 0 | H37: K_vqt | I37: (c‡bi j¶ ... nvRvi Ewbk UvKv gvÎ )
D39: ='MisC Cal-2'!F63 -> †iqvZ‡hvM¨ wewb‡qvM I e¨q | E39: 990235
C41: Tax Credits & Refund (Input) | H41: †bvwUk/dg©/wewea dg© wcÖ›U
D42: we‡qvRbt | E42: Dr‡m KwZ©Z Ki | F42: hZ †ewk AwMÖg Ki, Kg‡e mij my‡`i Wi ! | H42: A¨v‡mm‡g›U wi‡j‡UW †bvwUk/dg© | J42: wewea †bvwUk/dg©
D43: =D33 -> wbqwgZ Drm n‡Z ‡gvU Avq (163 avivi Avq e¨wZZ) | E43: =F33 -> 84000 | H43: wiUvb© cÖ‡mm †bvwUk | J43: 183(3) avivq ïbvbxi †bvwUk
D44: 152/154 avivq AwMÖg AvqKi | E44: 400000 | H44: Sheet of Computation | J44: 179 avivi †bvwUk
D45: 153 avivq Mvwoi AwMÖg AvqKi | E45: 75000 | H45: AvB.wU.-15 (wiUvb© cÖ‡mm) | J45: 172 avivi †bvwUk (AvB.wU.-10)
D46: wiUv‡b©i mv‡_ 173 avivq cÖ`Ë AvqKi | E46: 0 | H46: Ki cwiMYbv cÎ (AvB.wU.-30) | J46: 280 avivi Rwigvbvi †bvwUk
D47: c~e©eZ©x Kie‡l© D™¢‚Z cÖZ¨vc©Y/mgš^q Ki | E47: 180000 | F47: 2022-23 | H47: wWgvÛ †bvwUk (AvB.wU.-15) | J47: 212 avivq cybtD‡b¥vPb †bvwUk
C49: MicS Input | H49: wewea †bvwUk/ ïbvbxi Rb¨ mgq | J49: wWgvÛ †bvwU‡k cÖ`Ë mgq
C50: †h avivq Ki wba©viYt | F50: 82wewe/82wm (AvqKi Aa¨v‡`k, 1984)/183(7)
E51: 191(4), 143(2)(K), 267, 266, 269, 270, 271, 272, 273, 274, 275 avivq Rwigvbvt | F51: 0 | H51: w`b | I51: 22 | J51: w`b | K51: 27
E52: 214(4) avivq my`t | F52: 0
E53: (we‡kl †Kvb avivq hw` Ki`vq cÖ‡hvR¨ nq) Ab¨vb¨ AsK: | F53: 0
C56: e¨envi wewat | D56: 1. †Kej mv`v Kvjv‡ii N‡i WvUv BbcyU Kiv hv‡e| | I56: Any Query: mrahman.buet08@gmail.com Special Thanks: ACT/DCT: Tofayel Sir (34), Maniruzzaman(38), Istiaque(38), Shafiq(38), Nazirul(38) & Palash (UDA). For Latest Version Download:
D57: 2. A¨vKzq¨v Kvjv‡ii Ni¸‡jv‡Z, Wªc-WvDb K‡i wm‡j± Kiæb|
D58: 3. Tan color Gi Ni AcwieZ©bxq|
I61: https://tinyurl.com/easypeasytax

Sheet Sheet of Calculation
B1: cwiMYbv cÎ (Sheet of Computation)
A2: Kiel©: | B2: ='MisC Intrst-3'!L3 -> 2025-26 | E2: ZvwiL: | F2: =TEXT('Data Input'!F5,"dd/mm/yyyy") -> 30/12/2026
A3: bvg: | B3: ="Rbve "&'Data Input'!D6 -> Rbve Rbve †gvt bvCg nvmvb | D3: ='Data Input'!F8 -> Individual | E3: wUAvBGb: | F3: ='Data Input'!F4&"/Ktmvt-"&'Data Input'!K4 -> 387493583464/Ktmvt-16
A4: wVKvbv: | B4: ='Data Input'!D7 | E4: aiY: | F4: ='Data Input'!D8 -> পুরুষ
B5: Zdwmj-1 (†eZbvw`) | F5: (UvKv)
B6: †emiKvwi PvKwi n‡Z Avq (‡eZb I fvZvw`) | D6: ='Data Input'!E14 -> Av‡qi cwigvY | E6: Ki-Ae¨vnwZ cÖvß Avq | F6: wbU Ki‡hvM¨ Avq
B7: ='Data Input'!D15 -> মূল বেতন/মজুরি/পারিশ্রমিক ইত্যাদি | D7: ='MisC Cal-1'!I83 -> 1600000 | E7: ='MisC Cal-1'!J83 -> 0 | F7: ='MisC Cal-1'!K83 -> 1600000
B8: ='Data Input'!D16 -> মোটরগাড়ি প্রতি সুবিধা | D8: ='MisC Cal-1'!I84 -> 0 | E8: ='MisC Cal-1'!J84 -> 0 | F8: ='MisC Cal-1'!K84 -> 0
B9: ='Data Input'!D17 -> বাড়ি ভাড়া ভাতা | D9: ='MisC Cal-1'!I85 -> 0 | E9: ='MisC Cal-1'!J85 -> 0 | F9: ='MisC Cal-1'!K85 -> 0
B10: ='Data Input'!D18 -> চিকিৎসা ভাতা/পারকুইজিট ইত্যাদি | D10: ='MisC Cal-1'!I86 -> 0 | E10: ='MisC Cal-1'!J86 -> 0 | F10: ='MisC Cal-1'!K86 -> 0
B11: ='Data Input'!D19 -> উৎসব/উৎসাহ বোনাস/অন্যান্য ইত্যাদি | D11: ='MisC Cal-1'!I87 -> 0 | E11: ='MisC Cal-1'!J87 -> 0 | F11: ='MisC Cal-1'!K87 -> 0
B12: ='Data Input'!D20 -> সম্পূর্ণ করযোগ্য ভাতা/ভাতা সমূহ | D12: ='MisC Cal-1'!I88 -> 0 | E12: ='MisC Cal-1'!J88 -> 0 | F12: ='MisC Cal-1'!K88 -> 0
B13: ='Data Input'!D21 -> আনুতোষিক/অ্যানুইটি, পেনশন বা ইহাদের সম্পূরক (করমুক্ত) | D13: ='MisC Cal-1'!I89 -> 0 | E13: ='MisC Cal-1'!J89 -> 0 | F13: ='MisC Cal-1'!K89 -> 0
B14: ='Data Input'!D22 -> †gvU Avq = | D14: ='MisC Cal-1'!I94 -> 1600000 | E14: ='MisC Cal-1'!J94 -> 500000 | F14: ='MisC Cal-1'!K94 -> 1100000
B16: ='Data Input'!D25 -> LvZ wfwËK Avq | D16: Ki‡hvM¨ Avq | E16: Dr‡m KwZ©Z Ki | F16: aiY
B17: ='Data Input'!D26 -> †emiKvwi PvKwi n‡Z Ki‡hvM¨ †gvU Avq | D17: =F14 -> 1100000 | E17: =IF(D17<'Data Input'!F26,0,'Data Input'!F26) -> 9000 | F17: (32,33,34 avivi Avq)
B18: ='Data Input'!D27 -> (সরকারি/সমমান) চাকরি হতে করযোগ্য আয় | D18: ='Data Input'!E27 -> 0 | E18: ='Data Input'!F27 -> 0 | F18: =_xlfn.XLOOKUP(B18,'MisC Cal-1'!B121:B131,'MisC Cal-1'!C121:C131,0,1) -> (32 avivi Avq)
B19: ='Data Input'!D28 -> পেশাগত আয় | D19: ='Data Input'!E28 -> 3862355 | E19: =IF(D19<'Data Input'!F28,0,'Data Input'!F28) -> 75000 | F19: =_xlfn.XLOOKUP(B19,'MisC Cal-1'!B121:B131,'MisC Cal-1'!C121:C131,0,1) -> (cÂg Aa¨v‡qi Avq)
B20: ='Data Input'!D29 -> মূলধনী আয় (নিয়মিত করদায়ভুক্ত) | D20: ='Data Input'!E29 -> 0 | E20: =IF(D20<'Data Input'!F29,0,'Data Input'!F29) -> 0 | F20: =_xlfn.XLOOKUP(B20,'MisC Cal-1'!B121:B131,'MisC Cal-1'!C121:C131,0,1) -> (58 avivi Avq)
B21: ='Data Input'!D30 -> অন্যান্য খাতের আয় | D21: ='Data Input'!E30 -> 0 | E21: ='Data Input'!F30 -> 0 | F21: =_xlfn.XLOOKUP(B21,'MisC Cal-1'!B121:B131,'MisC Cal-1'!C121:C131,0,1) -> (66 avivi Avq)
B22: ='Data Input'!D31 -> ব্যক্তিসংঘ/ফার্মের করারোপিত শেয়ার আয় | C22: (Taxed Income) | D22: ='Data Input'!E31 -> 500000 | E22: ='Data Input'!F31 -> 0 | F22: (80 avivi Avq)
B23: ='Data Input'!D32 -> ৫৬/৭৬(৬) ধারায় নিয়মিত করদায়ভুক্ত আয় | D23: ='Data Input'!E32 -> 0 | E23: ='Data Input'!F32 -> 0 | F23: ='MisC Cal-1'!C134 -> (55,56,76(6) aviq Avq)
B24: ='Data Input'!D33 -> wbqwgZ Drm n‡Z ‡gvU Avq (163 avivi Avq e¨wZZ) | D24: =IF((SUM(D17:D23))>1,SUM(D17:D23),1) -> 5462355 | E24: =SUM(E17:E23) -> 84000
B25: ='Data Input'!D35 -> আর্থিক পরিসম্পদ হতে ১৬৩ ধারার আয় | D25: ='Data Input'!E35 -> 1728142 | E25: ='Data Input'!F35 -> 180000 | F25: (b¨~bZg Ki`vq)
B26: ='Data Input'!D36 -> ‡gvU Avq (163 avivi b¨~bZg Ki`vqfz³ Avq mn) | D26: =SUM(D24:D25) -> 7190497
B27: ='Data Input'!D37 -> * 163 avivi P‚ovšÍ Ki`vq Avq (mÂqc‡Îi gybvdv, BZ¨vw`) | D27: ='Data Input'!E37 -> 0 | E27: ='Data Input'!F37 -> 0 | F27: (P‚ovšÍ Ki`vqfz³)
B29: Ki cwiMYbv | D29: avc | E29: nvi | F29: Ki (UvKv)
C30: =D24 -> 5462355 | D30: ='MisC Cal-1'!D67 -> 350000 | E30: ='MisC Cal-1'!E67 -> 0 | F30: =MIN(C30:D30)*E30 -> 0
C31: =IF(C30>D30,(C30-D30),0) -> 5112355 | D31: ='MisC Cal-1'!D68 -> 100000 | E31: ='MisC Cal-1'!E68 -> 0.05 | F31: =MIN(C31:D31)*E31 -> 5000
C32: =IF(C31>D31,(C31-D31),0) -> 5012355 | D32: ='MisC Cal-1'!D69 -> 400000 | E32: ='MisC Cal-1'!E69 -> 0.1 | F32: =MIN(C32:D32)*E32 -> 40000
C33: =IF(C32>D32,(C32-D32),0) -> 4612355 | D33: ='MisC Cal-1'!D70 -> 500000 | E33: ='MisC Cal-1'!E70 -> 0.15 | F33: =MIN(C33:D33)*E33 -> 75000
C34: =IF(C33>D33,(C33-D33),0) -> 4112355 | D34: ='MisC Cal-1'!D71 -> 500000 | E34: ='MisC Cal-1'!E71 -> 0.2 | F34: =MIN(C34:D34)*E34 -> 100000
C35: =IF(C34>D34,(C34-D34),0) -> 3612355 | D35: ='MisC Cal-1'!D72 -> 2000000 | E35: ='MisC Cal-1'!E72 -> 0.25 | F35: =_xlfn.XLOOKUP('MisC Intrst-3'!L3,'MisC Intrst-3'!R10:R23,'MisC Intrst-3'!AQ10:AQ23,0) -> 500000
C36: =IF(C35>D35,(C35-D35),0) -> 1612355 | D36: ='MisC Cal-1'!D73 -> Aewkó | E36: ='MisC Cal-1'!E73 -> 0.3 | F36: =IF(C36>0,(C36*E36),0) -> 483706.5
C37: ='MisC Cal-1'!K5 -> 0 | D37: AvqKi (wbqwgZ Dr‡mi Avq n‡Z) | F37: ='MisC Cal-1'!L8 -> 1203706.5
B38: 163 avivi cÖv°wjZ AvqKi (b¨~bZg Ki`vq) | F38: ='MisC Cal-1'!F18 -> 518442.6
B39: 163 avivi AvqKi (mÂqc‡Îi gybvdv BZ¨vw`)/(P‚ovšÍ Ki`vq) | F39: ='MisC Cal-1'!F19 -> 0
B40: †iqvZ c~e©eZ©x AvqKi (wbqwgZ/AbywgZ, b¨~bZg I P‚ovšÍ Ki`vq) | F40: =F37+F38+F39 -> 1722149.1
B41: ='MisC Cal-2'!C76 -> *(e¨w³msN/dv‡g©i Av‡qi Rb¨ Ki Ae¨vnwZ = 110183/-) | E41: Ki †iqvZ (ev`) | F41: =F58 -> 258717.26
B42: †iqvZ cieZ©x AvqKi (wbqwgZ/AbywgZ, b¨~bZg I P‚ovšÍ) | D42: /b¨~bZg Ki`vq = | E42: ="( "&'Data Input'!I6&"/- UvKv )" -> ( 4000/- UvKv ) | F42: ='MisC Cal-1'!E35 -> 1463431.8
B43: mviPvR© (‡hvM) | F43: ='MisC Cal-2'!D10 -> 0
B44: ='MisC Intrst-3'!T32&" ‡gvU AvqKi " -> ‡gvU AvqKi | F44: =F42+F43 -> 1463431.8
B46: Ki`vq we‡qvRb | D46: Ki`vq †hvM/mgš^q
B47: †gvU Dr‡m KwZ©Z Ki (wbqwgZ + 163 aviv) | C47: ='MisC Cal-1'!O15+'MisC Cal-1'!O16 -> 264000 | D47: 160 Ges 162 avivq my` | F47: ='MisC Intrst-3'!D18 -> 53835.202
B48: ='Data Input'!D44 -> 152/154 avivq AwMÖg AvqKi | C48: ='Data Input'!E44 -> 400000 | D48: ='MisC Intrst-3'!T32&" wej¤^ my`" -> wej¤^ my` | F48: ='MisC Intrst-3'!L43 -> 0
B49: ='Data Input'!D45 -> 153 avivq Mvwoi AwMÖg AvqKi | C49: ='Data Input'!E45 -> 75000 | D49: cwi‡ek mviPvR© | F49: ='MisC Cal-2'!D11 -> 0
B50: ='Data Input'!D46 -> wiUv‡b©i mv‡_ 173 avivq cÖ`Ë AvqKi | C50: ='Data Input'!E46 -> 0 | D50: Rwigvbv/214(4) avivq my`/Ab¨vb¨ Ki`vq | F50: ='Data Input'!I35+'Data Input'!K35 -> 0
B51: bxU AvqKi | C51: ='MisC Cal-1'!L23 -> 724431.84 | D51: =IF(F51>0,"("&'Data Input'!F47&" Kie‡l©i)",0) -> (2022-23 Kie‡l©i) | E51: cÖZ¨vc©Y/mgš^q Ki (ev`) | F51: ='Data Input'!E47 -> 180000
B52: ="K_vqt "&'Data Input'!I37 -> K_vqt (c‡bi j¶ ... nvRvi Ewbk UvKv gvÎ ) | E52: cÖ‡`q AvqKi | F52: =C51+(F47+F48+F49+F50)-F51 -> 598267.04
B54: =TEXT('MisC Intrst-3'!N4,"dd/mm/yyyy")&" wLªt Zvwi‡L Ki`vZvi bxU m¤c`" -> 30/06/2025 wLªt Zvwi‡L Ki`vZvi bxU m¤c` | C54: ='MisC Cal-2'!D6 -> <= ৪ কোটি | E54: wiUvb© `vwL‡ji ZvwiLt | F54: ='MisC Intrst-3'!L4 -> 45962
B56: Ki †iqvZ cwiMYbv | E56: ='MisC Cal-2'!C66 -> Aby‡gvw`Z wewb‡qvM I e¨q = 148535.25/- | F56: ='MisC Cal-2'!D67 -> 148535.25
B57: ='MisC Cal-2'!C61 -> wbqwgZ ‡gvU Avq (163 Avq e¨wZZ) | C57: ='MisC Cal-2'!D61 -> 12152852 | E57: ='MisC Cal-2'!C68 -> e¨w³msN/dv‡g©i Av‡qi Rb¨ Ki Ae¨vnwZ | F57: ='MisC Cal-2'!D68 -> 110182.01
B58: ='MisC Cal-2'!C62 -> wbqwgZ ‡gvU Av‡qi 3% | C58: ='MisC Cal-2'!D62 -> 364585.56 | E58: ‡gvU †iqvZ | F58: ='MisC Cal-2'!D69 -> 258717.26
B59: ='MisC Cal-2'!C63 -> ev, †iqvZ‡hvM¨ (wewb‡qvM I e¨‡qi) 15% | C59: ='MisC Cal-2'!D63 -> 148535.25
B60: ='MisC Cal-2'!C64 -> ev, 10 j¶ UvKv | C60: ='MisC Cal-2'!D64 -> 1000000 | D60: c„ôv- 02 | E60: (AvqKi AvBb, 2023 Abyhvqx)

Sheet Return Process
E3: ='MisC Cal-1'!G143 -> MYcÖRvZš¿x evsjv‡`k miKvi | J3: RvZxq ivR¯^ †evW© www.nbr.gov.bd | O3: AvB.wU-15(2023)
E4: ='MisC Cal-1'!G144 -> DcKi Kwgkbv‡ii Kvh©vjq
E5: ='MisC Cal-1'!G145 -> কর সার্কেল-16, কর অঞ্চল-খুলনা
E6: ='MisC Cal-1'!G146 -> 50/1, wfAvBwc †ivW, bqvcëb, XvKv| | J6: AvqKi AvBb, 2023 Gi 214 Abyhvqx `vex/cÖZ¨c©Y Gi †bvwUk
A8: bw_ bs - | B8: ="witcÖt/"&'Sheet of Calculation'!F3&"/"&'Data Input'!K25&"/" -> witcÖt/387493583464/Ktmvt-16/0/ | G8: ZvwiL t | H8: =TEXT('Data Input'!F5,"dd/mm/yyyy") -> 30/12/2026 | I8: wLªt | J8: bs: | K8: ="wWt‡bvt/"&'Data Input'!F4&"/mv-"&'Data Input'!K4&"/"&'Data Input'!K25&"/" -> wWt‡bvt/387493583464/mv-16/0/ | N8: ZvwiLt | O8: =TEXT('Data Input'!F5,"dd/mm/yyyy") -> 30/12/2026
A9: Ki`vZvi bvg t | B9: ='Data Input'!D6 -> Rbve †gvt bvCg nvmvb | J9: cÖwZ
A10: wU.AvB.Gb t | B10: ='Data Input'!F4&"/Ktmvt-"&'Data Input'!K4 -> 387493583464/Ktmvt-16
A11: Kiel© t | B11: ='Data Input'!D4 -> 2025-26 | J11: Ki`vZvi bvg: | K11: ='Data Input'!D6 -> Rbve †gvt bvCg nvmvb
A12: wVKvbv t | B12: ='Data Input'!D7 | J12: wVKvbv: | K12: ='Data Input'!D7
A14: welqt | B14: ="Ki`vZv KZ©…K AvqKi AvBb, 2023 Gi 180(1) avivbymv‡i `vwLjK…Z "&'Data Input'!D4&" Kie‡l©i ¯^wba©viYx wiUvb©wU, AvqKi AvBb, 2023 Gi 181(1) avivq cÖwµqvKiYc~e©K 181(2) avivq AewnZKiY|" -> Ki`vZv KZ©…K AvqKi AvBb, 2023 Gi 180(1) avivbymv‡i `vwLjK…Z 2025-26 Kie‡l©i ¯^wba©viYx wiUvb©wU, AvqKi AvBb, 2023 Gi 181(1) avivq cÖwµqvKiYc~e©K 181(2) avivq AewnZKiY| | J14: wU.AvB.Gb: | K14: ='Data Input'!F4&"/Ktmvt-"&'Data Input'!K4 -> 387493583464/Ktmvt-16
J15: Kiel©: | K15: ='Data Input'!D4 -> 2025-26
A17: m¤§vwbZ Ki`vZv, | J17: ="1| GZØviv Avcbv‡K Rvbv‡bv hvB‡Z‡Q †h, UvKv "&'Data Input'!K36&"/- "&'Sheet of Calculation'!B52&" hvnv "&'Data Input'!D4&" Kie‡l©i Rb¨ Avcbvi cÖ‡`q/Avcbvi wbKU †dir‡hvM¨ wnmv‡e wbgœiƒc avh© Kiv nBqv‡Qt" -> 1| GZØviv Avcbv‡K Rvbv‡bv hvB‡Z‡Q †h, UvKv 598267/- K_vqt (c‡bi j¶ ... nvRvi Ewbk UvKv gvÎ ) hvnv 2025-26 Kie‡l©i Rb¨ Avcbvi cÖ‡`q/Avcbvi wbKU †dir‡hvM¨ wnmv‡e wbgœiƒc avh© Kiv nBqv‡Qt
A18: Dchy©³ wel‡qi cÖwZ Avcbvi `„wó AvKl©Y KiwQ|
A19: ="1. "&'Data Input'!D4&" Kie‡l© ¯^wba©viYx c×wZ‡Z Avcbvi `vwLjK…Z wiUvb©/ms‡kvwaZ wiUvb©wU, AvqKi AvBb, 2023 Gi 181(1) avivq cÖwµqvKiY c~e©K MvwYwZK ÎæwU/wiUv‡b©i mv‡_ `vwLjK…Z wee„wZ ev `wjjvw`‡Z we`¨gvb/Zv n‡Z D™¢‚Z Z‡_¨i Av‡jv‡K wbgœiƒc Aï× `vwe cwijw¶Z n‡q‡Q|" -> 1. 2025-26 Kie‡l© ¯^wba©viYx c×wZ‡Z Avcbvi `vwLjK…Z wiUvb©/ms‡kvwaZ wiUvb©wU, AvqKi AvBb, 2023 Gi 181(1) avivq cÖwµqvKiY c~e©K MvwYwZK ÎæwU/wiUv‡b©i mv‡_ `vwLjK…Z wee„wZ ev `wjjvw`‡Z we`¨gvb/Zv n‡Z D™¢‚Z Z‡_¨i Av‡jv‡K wbgœiƒc Aï× `vwe cwijw¶Z n‡q‡Q|
J21: AvqKi/cÖZ¨c©Y†hvM¨ Ki: | L21: 180(1)/181(2)/181(3)(M) [wiUvb© cÖ‡mm] | N21: UvKv: | O21: ='Sheet of Calculation'!C51 -> 724431.84
A22: (K) AvqKi cwiMYbvq Kg Avq/Kg Ki/‡ewk †iqvZ/fzjfv‡e Ki wba©viY K‡i‡Qb| | J22: 191(4), 143(2)(K), 267, 266, 269, 270, 271, 272, 273, 274, 275 avivq Rwigvbvt | N22: UvKv: | O22: ='Data Input'!F51 -> 0
A24: 2. DwjøwLZ MvwYwZK ÎæwU/Aï× `vwe ms‡kvab K‡i, Avcbvi cÖ`wk©Z Avq I cÖ‡`q AvqKi I Ab¨vb¨ cwigvY AsK Ges AÎ Kvh©vjq KZ©…K wbiƒwcZ Avq I cÖ‡`q AvqKi I Ab¨vb¨ cwigvY As‡Ki wnmv‡ei "cwiMYbv cÎ (Sheet of Computation)" GB †bvwU‡ki mv‡_ mshy³ Av‡Q| | J24: 160, 162, 214(4) avivq my`: .................. | N24: UvKv: | O24: ='Data Input'!I32+'Data Input'!F52 -> 53835.202
J25: ="mviPvR©:"&'MisC Cal-2'!C15&" /Ab¨vb¨ AsK: "&'MisC Intrst-3'!R32&"...." -> mviPvR©:. /Ab¨vb¨ AsK: .... | N25: UvKv: | O25: ='Data Input'!I34+'Data Input'!F53+'Data Input'!K34 -> 0
J27: ="২। আপনাকে এই টাকা আগামী "&TEXT('MisC Intrst-3'!L27,"dd/mm/yyyy")&" খ্রিঃ তারিখে বা তৎপূর্বে এ চালানে/সরকারি কোষাগারে: কর অঞ্চলঃ "&'Data Input'!K5&"- এর কোডে ( "&'Data Input'!K8&" ) জমা দিতে হইবে।" -> ২। আপনাকে এই টাকা আগামী 26/01/2027 খ্রিঃ তারিখে বা তৎপূর্বে এ চালানে/সরকারি কোষাগারে: কর অঞ্চলঃ খুলনা- এর কোডে ( 1-1141-0055-0১১১ ) জমা দিতে হইবে।
A28: ="3. DwjøwLZ MvwYwZK ÎæwU/Aï× `vwe Gi †cÖw¶‡Z wbiƒwcZ Avq I cÖ‡`q AvqK‡ii wel‡q Avcbvi e³e¨/AvcwË/wjwLZ e¨vL¨v/cÖgvYvw` A_ev cwi‡kva‡hvM¨ Ki ( "&'Data Input'!K36&"/- UvKv cwi‡kv‡ai Pvjvb cÎ)/Ki mn, AvqKi AvBb, 2023 Gi aviv 181(2)(M)(A) Abymv‡i ms‡kvwaZ wiUvb©, AvMvgx "&TEXT('MisC Intrst-3'!L26,"dd/mm/yyyy")&" wLªt Zvwi‡L ev Zrc~‡e© g‡a¨ wb‡R/‡iwRwóª WvK‡hv‡M/evnK gvidZ wbgœ¯^v¶iKvixi eivei †cÖi‡Yi Rb¨ Aby‡iva KiwQ|" -> 3. DwjøwLZ MvwYwZK ÎæwU/Aï× `vwe Gi †cÖw¶‡Z wbiƒwcZ Avq I cÖ‡`q AvqK‡ii wel‡q Avcbvi e³e¨/AvcwË/wjwLZ e¨vL¨v/cÖgvYvw` A_ev cwi‡kva‡hvM¨ Ki ( 598267/- UvKv cwi‡kv‡ai Pvjvb cÎ)/Ki mn, AvqKi AvBb, 2023 Gi aviv 181(2)(M)(A) Abymv‡i ms‡kvwaZ wiUvb©, AvMvgx 21/01/2027 wLªt Zvwi‡L ev Zrc~‡e© g‡a¨ wb‡R/‡iwRwóª WvK‡hv‡M/evnK gvidZ wbgœ¯^v¶iKvixi eivei †cÖi‡Yi Rb¨ Aby‡iva KiwQ|
J32: ="২। আপনি যদি ধার্যকৃত করের/জরিমানার অথবা ধার্যকৃত সুদের আদেশের বিরুদ্ধে আপিল দায়ের করিতে ইচ্ছুক হন, তাহা হইলে এই নোটিশ প্রাপ্তির ৪৫ দিনের মধ্যে আপিল অতিরিক্ত/ যুগ্ন কর কমিশনার, রেঞ্জঃ "&'Data Input'!K11&" / কর কমিশনার (আপিল), কর আপিল অঞ্চল -"&'Data Input'!I11&" -এর নিকট আপিল দায়ের করিতে পারিবেন। " -> ২। আপনি যদি ধার্যকৃত করের/জরিমানার অথবা ধার্যকৃত সুদের আদেশের বিরুদ্ধে আপিল দায়ের করিতে ইচ্ছুক হন, তাহা হইলে এই নোটিশ প্রাপ্তির ৪৫ দিনের মধ্যে আপিল অতিরিক্ত/ যুগ্ন কর কমিশনার, রেঞ্জঃ 3 / কর কমিশনার (আপিল), কর আপিল অঞ্চল -খুলনা -এর নিকট আপিল দায়ের করিতে পারিবেন।
A35: ="4. D³ Zvwi‡Li g‡a¨ Avcbvi wjwLZ e¨vL¨v/cÖgvYvw`/cwi‡kva‡hvM¨ Ki ( "&'Data Input'!K36&"/- UvKv)/ Kimn, ms‡kvwaZ wiUvb© †cÖiY Kiv bv n‡j, AvqKi Awdm KZ©…K Avcbvi wiUv‡b© mbv³K…Z MvwYwZK ÎæwU/Aï× `vwe mwVK e‡j we‡ewPZ n‡e Ges Gi wfwË‡Z cieZ©x‡Z Avcbvi eivei `vwe bvgv †bvwUk †cÖiY Kiv n‡e|" -> 4. D³ Zvwi‡Li g‡a¨ Avcbvi wjwLZ e¨vL¨v/cÖgvYvw`/cwi‡kva‡hvM¨ Ki ( 598267/- UvKv)/ Kimn, ms‡kvwaZ wiUvb© †cÖiY Kiv bv n‡j, AvqKi Awdm KZ©…K Avcbvi wiUv‡b© mbv³K…Z MvwYwZK ÎæwU/Aï× `vwe mwVK e‡j we‡ewPZ n‡e Ges Gi wfwË‡Z cieZ©x‡Z Avcbvi eivei `vwe bvgv †bvwUk †cÖiY Kiv n‡e|
J38: ৩। আপিলাদেশের বিরুদ্ধে আপীল দায়ের করিতে ইচ্ছুক হইলে উক্ত আপিলাদেশ প্রাপ্তির ৬০ দিনের মধ্যে কর আপিলাত ট্রাইব্যুনাল এর নিকট আপীল দায়ের করিতে পারিবেন।
A40: ivR¯^ Avni‡Y Avcbvi mn‡hvwMZv GKvšÍ Kvg¨|
A42: cwi‡kva‡hvM¨ Kit | B42: ='Data Input'!K36 -> 598267 | C42: /- UvKv
A43: K_vqt | B43: ='Data Input'!I37 -> (c‡bi j¶ ... nvRvi Ewbk UvKv gvÎ )
A44: Ki cwi‡kva †KvWt | B44: ='Data Input'!K8 -> 1-1141-0055-0১১১ | H44: ='MisC Cal-1'!D142 -> ()
H45: ='Data Input'!I5 -> উপ কর কমিশনার | N45: Dc Ki Kwgkbvi
H46: ='MisC Cal-1'!D144 -> Ki mv‡K©j-16, | N46: (bvg, ¯^v¶i I mxj)
H47: ='MisC Cal-1'!D145 -> কর অঞ্চল-খুলনা।
H48: ='MisC Cal-1'!D146 -> †dvbt 02-2222244444
N51: ='MisC Cal-1'!D146 -> †dvbt 02-2222244444
E52: Scan this QR Code/go to this link or recalculate tax by yourself for this document: | J52: (Awd‡mi mxj †gvni) | M52: B-‡gBj | N52: . . . . . . . . . . . . . . . . . . .
E53: ='Data Input'!K7 -> https://tinyurl.com/easypeasytax | M53: wVKvbv | N53: ='MisC Cal-1'!G146 -> 50/1, wfAvBwc †ivW, bqvcëb, XvKv|
I54: (Aci c„ôv `ªóe¨)

Sheet I.T.-30
E1: AvB.wU-30 | J1: AvB.wU-30
A2: Ki/cÖZ¨c©Y cwiMYbv dig
A3: bvg: | B3: ='Sheet of Calculation'!B3 -> Rbve Rbve †gvt bvCg nvmvb | D3: aiY: | E3: ='Data Input'!D8 -> পুরুষ | F3: we‡qvRb Kiæb:
A4: wVKvbv: | B4: ='Data Input'!D7 | D4: †h avivq Ki wba©viY: | E4: ='Data Input'!F50 -> 82wewe/82wm (AvqKi Aa¨v‡`k, 1984)/183(7) | F4: (K) †gvU Dr‡m KwZ©Z Ki (wbqwgZ+163 avivi Ki) | I4: Uv: | J4: ='MisC Cal-1'!O15+'MisC Cal-1'!O16 -> 264000
F5: (L) 152/154/153 avivq AwMÖg AvqKi cwi‡kva | I5: Uv: | J5: ='Data Input'!E44+'Data Input'!E45 -> 475000
A6: B-wU.AvB.Gb: | B6: ='Data Input'!F4&"/Ktmvt-"&'Data Input'!K4 -> 387493583464/Ktmvt-16 | D6: wiUv‡b©i aiY | E6: ='Data Input'!D9 -> স্বনির্ধারণী | F6: (M) wiUv‡b©i mv‡_ 173 avivq cÖ`Ë AvqKi | I6: Uv: | J6: ='Data Input'!E46 -> 0
A7: Kiel©: | B7: ='Data Input'!D4 -> 2025-26 | D7: bxU m¤c`: | E7: =IF(E38=0,'MisC Cal-2'!F14,'Data Input'!D10) -> প্রযোজ্য নহে | F7: (N) cÖZ¨vc©Y/mgš^q Ki (hw` _v‡K) | I7: Uv: | J7: ='Data Input'!E47 -> 180000
A8: wiUvb© `vwL‡ji ZvwiL: | B8: ='Data Input'!D5 -> 45962 | D8: Ki w`em | E8: ='MisC Intrst-3'!L34 -> 45991 | H8: cwi‡kvwaZ †gvU AvqKi: | I8: Uv: | J8: =J4+J5+J6+J7 -> 919000
H9: Aewkó cÖ‡`q AvqKi: | I9: Uv: | J9: =E39-J8 -> 544431.84
A10: Av‡qi LvZmg~nt | C10: wbU Ki‡hvM¨ Avq | D10: 163 avivi Avq | E10: wbqwgZ Dr‡mi Avq | F10: 160 Ges 162 avivbymv‡i my`t
A11: ='Sheet of Calculation'!B17 -> †emiKvwi PvKwi n‡Z Ki‡hvM¨ †gvU Avq | C11: ='Data Input'!E26 -> 1100000 | D11: 0 | E11: =C11 -> 1100000 | F11: 1| Ki wba©vi‡Yi wfwË‡Z cÖ‡`q K‡ii 75% | H11: Uv: | I11: ='MisC Intrst-3'!H6 -> 1097573.9
A12: ='Sheet of Calculation'!B18 -> (সরকারি/সমমান) চাকরি হতে করযোগ্য আয় | C12: ='Data Input'!E27 -> 0 | D12: 0 | E12: =C12 -> 0 | F12: 2| 152, 154 ev 153 avivbymv‡i cÖ`Ë Ki | H12: Uv: | I12: =J5 -> 475000
A13: ='Sheet of Calculation'!B19 -> পেশাগত আয় | C13: ='Data Input'!E28 -> 3862355 | D13: 0 | E13: =C13 -> 3862355 | F13: 3| Dr‡m AvqKi cwi‡kva | H13: Uv: | I13: =J4 -> 264000
A14: ='Sheet of Calculation'!B20 -> মূলধনী আয় (নিয়মিত করদায়ভুক্ত) | C14: ='Data Input'!E29 -> 0 | D14: 0 | E14: =C14 -> 0 | F14: 4| 1 n‡Z (2) I (3) Gi †hvMd‡ji cv_©K¨ | H14: Uv: | I14: ='MisC Intrst-3'!H8 -> 358573.88
A15: ='Sheet of Calculation'!B21 -> অন্যান্য খাতের আয় | C15: ='Data Input'!E30 -> 0 | D15: 0 | E15: =C15 -> 0 | F15: D³ cv_©‡K¨i Dci cÖ‡hvR¨Zv Abymv‡i my‡`i nvi I cwigvY: | I15: ='MisC Intrst-3'!L9&"%" -> 10% | J15: ='MisC Intrst-3'!D18 -> 53835.202
A16: ='Sheet of Calculation'!B22 -> ব্যক্তিসংঘ/ফার্মের করারোপিত শেয়ার আয় | C16: ='Data Input'!E31 -> 500000 | D16: 0 | E16: =C16 -> 500000 | F16: ="(cÖ‡hvR¨ †¶‡Î) "&'MisC Intrst-3'!T32&" wej¤^ my`t " -> (cÖ‡hvR¨ †¶‡Î) wej¤^ my`t | I16: ='MisC Intrst-3'!L30 -> 0.02 | J16: ='MisC Intrst-3'!L43 -> 0
A17: ='Sheet of Calculation'!B23 -> ৫৬/৭৬(৬) ধারায় নিয়মিত করদায়ভুক্ত আয় | C17: ='Data Input'!E32 -> 0 | D17: 0 | E17: =C17 -> 0 | F17: (cÖ‡hvR¨ †¶‡Î) cwi‡ek mviPvR©t | J17: ='MisC Cal-2'!D11 -> 0
A18: ='Sheet of Calculation'!B25 -> আর্থিক পরিসম্পদ হতে ১৬৩ ধারার আয় | C18: ='Data Input'!E35 -> 1728142 | D18: =C18 -> 1728142 | E18: 0 | F18: Rwigvbv/214(4) avivq my`/Ab¨vb¨ Ki`vqt | J18: ='Data Input'!I35+'Data Input'!K35 -> 0
A19: ='Sheet of Calculation'!B27 -> * 163 avivi P‚ovšÍ Ki`vq Avq (mÂqc‡Îi gybvdv, BZ¨vw`) | C19: ='Data Input'!E37 -> 0 | D19: =C19 -> 0 | E19: 0 | H19: me©‡kl wbU Ki`vqt | I19: Uv: | J19: ='Data Input'!K36 -> 598267
A20: †gvU Avq Uv: | C20: ='Sheet of Calculation'!D26+'Sheet of Calculation'!D27 -> 7190497 | D20: =SUM(D18:D19) -> 1728142 | E20: ='Sheet of Calculation'!D24 -> 5462355 | F20: AvqKi wba©vi‡Yi ZvwiL: | H20: (K_vq:) | I20: ='Data Input'!I37 -> (c‡bi j¶ ... nvRvi Ewbk UvKv gvÎ )
A21: Ki cwiMYbv | F21: ='Data Input'!F5 -> 46386
A22: 163 aviv e¨ZxZ wbqwgZ Dr‡mi Av‡qi Dci AvqKit
C23: Avq | D23: nvi | E23: AvqKi
C24: ='Sheet of Calculation'!D30 -> 350000 | D24: ='Sheet of Calculation'!E30 -> 0 | E24: ='Sheet of Calculation'!F30 -> 0
C25: ='Sheet of Calculation'!D31 -> 100000 | D25: ='Sheet of Calculation'!E31 -> 0.05 | E25: ='Sheet of Calculation'!F31 -> 5000
C26: ='Sheet of Calculation'!D32 -> 400000 | D26: ='Sheet of Calculation'!E32 -> 0.1 | E26: ='Sheet of Calculation'!F32 -> 40000 | J26: ='MisC Cal-1'!D142 -> ()
C27: ='Sheet of Calculation'!D33 -> 500000 | D27: ='Sheet of Calculation'!E33 -> 0.15 | E27: ='Sheet of Calculation'!F33 -> 75000 | J27: ='Data Input'!I5 -> উপ কর কমিশনার
C28: ='Sheet of Calculation'!D34 -> 500000 | D28: ='Sheet of Calculation'!E34 -> 0.2 | E28: ='Sheet of Calculation'!F34 -> 100000 | J28: ='MisC Cal-1'!D144 -> Ki mv‡K©j-16,
C29: ='Sheet of Calculation'!D35 -> 2000000 | D29: ='Sheet of Calculation'!E35 -> 0.25 | E29: ='Sheet of Calculation'!F35 -> 500000 | J29: ='MisC Cal-1'!D145 -> কর অঞ্চল-খুলনা।
B30: ='MisC Cal-1'!K5 -> 0 | D30: AvqKi (wbqwgZ Dr‡mi Avq n‡Z) | E30: ='MisC Cal-1'!L8 -> 1203706.5
D31: 163 avivi cÖv°wjZ AvqKi (b¨~bZg Ki`vq): | E31: ='MisC Cal-1'!F18 -> 518442.6
D32: 163 avivi AvqKi/(c~‡e©i P‚ovšÍ Ki`vq): | E32: ='MisC Cal-1'!F19 -> 0
D33: †iqvZ c~e©eZ©x AvqKi (wbqwgZ/AbywgZ, b¨~bZg I P‚ovšÍ Ki`vq): | E33: ='Sheet of Calculation'!F40 -> 1722149.1
A34: Ki †iqvZ t
D35: †iqvZ‡hvM¨ Lv‡Z cÖK…Z wewb‡qv‡Mi cwigvY: | E35: ='Data Input'!E39 -> 990235
C36: ='MisC Cal-2'!C76 -> *(e¨w³msN/dv‡g©i Av‡qi Rb¨ Ki Ae¨vnwZ = 110183/-) | D36: Ki †iqvZ: | E36: ='MisC Cal-2'!D69 -> 258717.26
D37: †iqvZ cieZ©x AvqKi (wbqwgZ/AbywgZ, b¨~bZg I P‚ovšÍ): | E37: ='MisC Cal-1'!E35 -> 1463431.8
A38: ="("&IF(E38>0,'MisC Cal-2'!F13,'MisC Cal-2'!F14)&")" -> (প্রযোজ্য নহে) | D38: evwo/Mvwo/wbU cwim¤c` mviPvR© (‡hvM): | E38: ='MisC Cal-2'!D10 -> 0
D39: mviPvR©mn wbU Ki`vq: | E39: ='Sheet of Calculation'!F44 -> 1463431.8
C41: (Aci c„ôv `ªóe¨) | H41: c„ôv- 02

Sheet I.T.-15
A3: RvZxq ivR¯^ †evW© www.nbr.gov.bd | F3: AvB.wU-15(2023)
A4: AvqKi AvBb, 2023 Gi 214 Abyhvqx `vex/cÖZ¨c©Y Gi †bvwUk
A5: bs: | B5: ="wWt‡bvt/"&'Data Input'!F4&"/mv-"&'Data Input'!K4&"/"&'Data Input'!K25&"/" -> wWt‡bvt/387493583464/mv-16/0/ | E5: ZvwiLt | F5: =TEXT('Data Input'!F5,"dd/mm/yyyy") -> 30/12/2026
A6: cÖwZ
A7: Ki`vZvi bvg: | B7: ='Sheet of Calculation'!B3 -> Rbve Rbve †gvt bvCg nvmvb
A8: wVKvbv: | B8: ='Data Input'!D7
A9: wU.AvB.Gb: | B9: ='Data Input'!F4&"/Ktmvt-"&'Data Input'!K4 -> 387493583464/Ktmvt-16
A10: Kiel©: | B10: ='Data Input'!D4 -> 2025-26
A11: ="1| GZØviv Avcbv‡K Rvbv‡bv hvB‡Z‡Q †h, UvKv "&'Data Input'!K36&"/- "&'Sheet of Calculation'!B52&" hvnv "&'Data Input'!D4&" Kie‡l©i Rb¨ Avcbvi cÖ‡`q/Avcbvi wbKU †dir‡hvM¨ wnmv‡e wbgœiƒc avh© Kiv nBqv‡Qt" -> 1| GZØviv Avcbv‡K Rvbv‡bv hvB‡Z‡Q †h, UvKv 598267/- K_vqt (c‡bi j¶ ... nvRvi Ewbk UvKv gvÎ ) hvnv 2025-26 Kie‡l©i Rb¨ Avcbvi cÖ‡`q/Avcbvi wbKU †dir‡hvM¨ wnmv‡e wbgœiƒc avh© Kiv nBqv‡Qt
A13: AvqKi/cÖZ¨c©Y†hvM¨ Ki: | C13: ='Data Input'!F50 -> 82wewe/82wm (AvqKi Aa¨v‡`k, 1984)/183(7) | E13: UvKv: | F13: ='Sheet of Calculation'!C51 -> 724431.84
A14: 191(4), 143(2)(K), 267, 266, 269, 270, 271, 272, 273, 274, 275 avivq Rwigvbvt | E14: UvKv: | F14: ='Data Input'!F51 -> 0
A15: 160, 162, 214(4) avivq my`: .................. | E15: UvKv: | F15: ='Data Input'!I32+'Data Input'!F52 -> 53835.202
A16: ="mviPvR©:"&'MisC Cal-2'!C15&" / Ab¨vb¨ AsK: "&'MisC Intrst-3'!R32&"......" -> mviPvR©:. / Ab¨vb¨ AsK: ...... | E16: UvKv: | F16: ='Data Input'!I34+'Data Input'!F53+'Data Input'!K34 -> 0
A18: ="২। আপনাকে এই টাকা আগামী "&TEXT('MisC Intrst-3'!L27,"dd/mm/yyyy")&" খ্রিঃ তারিখে বা তৎপূর্বে এ চালানে/সরকারি কোষাগারে: কর অঞ্চলঃ "&'Data Input'!K5&"- এর কোডে ( "&'Data Input'!K8&" ) জমা দিতে হইবে।" -> ২। আপনাকে এই টাকা আগামী 26/01/2027 খ্রিঃ তারিখে বা তৎপূর্বে এ চালানে/সরকারি কোষাগারে: কর অঞ্চলঃ খুলনা- এর কোডে ( 1-1141-0055-0১১১ ) জমা দিতে হইবে।
A20: ="২। আপনি যদি ধার্যকৃত করের/জরিমানার অথবা ধার্যকৃত সুদের আদেশের বিরুদ্ধে আপিল দায়ের করিতে ইচ্ছুক হন, তাহা হইলে এই নোটিশ প্রাপ্তির ৪৫ দিনের মধ্যে আপিল অতিরিক্ত/ যুগ্ন কর কমিশনার, রেঞ্জঃ "&'Data Input'!K11&" / কর কমিশনার (আপিল), কর আপিল অঞ্চল -"&'Data Input'!I11&" -এর নিকট আপিল দায়ের করিতে পারিবেন। " -> ২। আপনি যদি ধার্যকৃত করের/জরিমানার অথবা ধার্যকৃত সুদের আদেশের বিরুদ্ধে আপিল দায়ের করিতে ইচ্ছুক হন, তাহা হইলে এই নোটিশ প্রাপ্তির ৪৫ দিনের মধ্যে আপিল অতিরিক্ত/ যুগ্ন কর কমিশনার, রেঞ্জঃ 3 / কর কমিশনার (আপিল), কর আপিল অঞ্চল -খুলনা -এর নিকট আপিল দায়ের করিতে পারিবেন।
A22: ৩। আপিলাদেশের বিরুদ্ধে আপীল দায়ের করিতে ইচ্ছুক হইলে উক্ত আপিলাদেশ প্রাপ্তির ৬০ দিনের মধ্যে কর আপিলাত ট্রাইব্যুনাল এর নিকট আপীল দায়ের করিতে পারিবেন।
B24: 45154
E26: Dc Ki Kwgkbvi
E27: (bvg, ¯^v¶i I mxj)
E33: ='MisC Cal-1'!D146 -> †dvbt 02-2222244444
B34: (Awd‡mi mxj †gvni) | D34: B‡gBjt | E34: ...............................
D35: wVKvbvt | E35: ='MisC Cal-1'!G146 -> 50/1, wfAvBwc †ivW, bqvcëb, XvKv|

Sheet 183(3),179 Notices
A2: RvZxq ivR¯^ †evW© www.nbr.gov.bd | I2: AvB.wU-86 (2023) | J2: RvZxq ivR¯^ †evW© www.nbr.gov.bd | R2: AvB.wU-13 (2023)
A5: AvqKi AvBb, 2023 Gi aviv 183 (3) Abyhvqx †bvwUk | J5: AvqKi AvBb, 2023 Gi aviv 179 Abyhvqx †bvwUk
A6: (AvqKi Awdm) | J6: (AvqKi Awdm)
A8: bs t | B8: ="ïbvbx/"&'Data Input'!F4&"/mv-"&'Data Input'!K4&"/"&'Data Input'!K25&"/" -> ïbvbx/387493583464/mv-16/0/ | H8: ZvwiLt | I8: =TEXT('Data Input'!F5,"dd/mm/yyyy") -> 30/12/2026 | J8: bs t | K8: ="wntewn/"&'Data Input'!F4&"/mv-"&'Data Input'!K4&"/"&'Data Input'!K25&"/" -> wntewn/387493583464/mv-16/0/ | Q8: ZvwiLt | R8: =TEXT('Data Input'!F5,"dd/mm/yyyy") -> 30/12/2026
A9: cÖwZ | J9: cÖwZ
A11: Ki`vZvi bvgt | B11: ='Data Input'!D6 -> Rbve †gvt bvCg nvmvb | J11: Ki`vZvi bvgt | K11: ='Data Input'!D6 -> Rbve †gvt bvCg nvmvb
A12: wVKvbvt | B12: ='Data Input'!D7 | J12: wVKvbvt | K12: ='Data Input'!D7
A14: wUAvBGbt | B14: ='Data Input'!F4&"/Ktmvt-"&'Data Input'!K4 -> 387493583464/Ktmvt-16 | J14: wUAvBGbt | K14: ='Data Input'!F4&"/Ktmvt-"&'Data Input'!K4 -> 387493583464/Ktmvt-16
A15: Kiel©t | B15: ='Data Input'!D4 -> 2025-26 | J15: Kiel©t | K15: ='Data Input'!D4 -> 2025-26
A17: Avcwb AvqKi AvBb, 2023 Gi Aax‡b wiUvb© `vwLj Kwiqv‡Qb, †mB cÖm‡½ AviI wKQz Z_¨ cÖ‡qvRb| | J17: ‡h‡nZz DcwiD³ Kie‡l©i AvqKi avh© cÖm‡½ AvqKi AvBb, 2023 Gi aviv 166, 175 ev 176 Abyhvqx
J18: Avcwb GKLvwb AvqKi wiUvb©`vwLj Kwiqv‡Qb/ aviv 172 ev 212 Abyhvqx …...................... wL&ª. ZvwiL hy³ GKwU
A19: ="AZGe "&TEXT('MisC Intrst-3'!L26,"dd/mm/yyyy")&" ZvwiL †ejv 11:00 NwUKvq Avcwb ¯^qs A_ev AvqKi AvBb, 2023 Gi 327 aviv Abyhvqx " -> AZGe 21/01/2027 ZvwiL †ejv 11:00 NwUKvq Avcwb ¯^qs A_ev AvqKi AvBb, 2023 Gi 327 aviv Abyhvqx | J19: †bvwUk …..................... Zvwi‡L Avcbvi Dci Rvix Kiv nBqv‡Q, D³ AvB‡bi aviv 179 Abyhvqx Avcbv‡K
A20: wjwLZfv‡e ¶gZvcÖvß †Kvb Aby‡gvw`Z cÖwZwbwa Dcw¯’Z nBqv wbgœ¯^v¶iKvixi wbKU AvqKi wiUvb© mswkøó `wjjcÎ, wnmv‡ei | J20: ="AewnZ Kiv hvB‡Z‡Q †h, wb¤œ¯^vÿiKvixi Awd‡m "&TEXT('MisC Intrst-3'!L26,"dd/mm/yyyy")&" wLª. ZvwiL c~e©vý/Acivý 11:00 NwUKvq " -> AewnZ Kiv hvB‡Z‡Q †h, wb¤œ¯^vÿiKvixi Awd‡m 21/01/2027 wLª. ZvwiL c~e©vý/Acivý 11:00 NwUKvq
A21: LvZv I Ab¨vb¨ cÖgvYvw` †ck Kivi Rb¨ Aby‡iva Rvbv‡bv nBj| | J21: wb¤œewY©Z wnmve ewn/`wjjvw` `vwLj Kwi‡eb|
A23: GB †bvwUk cwicvj‡b e¨_© nB‡j AvqKi AvBb, 2023 Gi 184 aviv Abyhvqx GKZidvfv‡e Ki wba©viY Kiv hvB‡Z cv‡i Ges | J23: GB †bvwUk cwicvj‡b e¨_© nB‡j AvqKi AvBb,2023 Gi aviv 270 Abyhvqx Rwigvbv Av‡iv‡ci weavb
A24: D³ AvB‡bi 270 aviv Abyhvqx Rwigvbv Av‡iv‡ci weavb iwnqv‡Q| | J24: iwnqv‡Q|
J26: wnmve ewn/`wjjvw`i weeiYt
J27: †eZb weeiYx/cÖZ¨qbcÎ/Ab¨vb¨;
J28: e¨vsK wnmve weeiYx/e¨vsK mgš^q weeiYx;
J29: wej/fvDPvivw`;
J30: Dr‡m KZ©b‡hvM¨ Li‡Pi Dci, Ki KZ©‡bi cÖgvYvw`;
H31: Dc Ki Kwgkbvi | J31: evox fvovi Pzw³cÎ/e¨vsK Rgvi cÖgvY; | Q31: Dc Ki Kwgkbvi
H32: (bvg, ¯^v¶i I mxj) | J32: Avg`vbx e¨emvi ¯^c‡¶ wej Ad Gw›Uª, wej Ad G‡mm‡g‡›Ui Kwc BZ¨vw`| | Q32: (bvg, ¯^v¶i I mxj)
J33: Ab¨vb¨ Av‡qi mg_©‡b cÖgvYvw`|
G41: ='MisC Cal-1'!D146 -> †dvbt 02-2222244444 | P41: ='MisC Cal-1'!D146 -> †dvbt 02-2222244444
A42: (Awd‡mi mxj †gvni) | F42: B-‡gBj | G42: . . . . . . . . . . . . . . . . . . . | J42: (Awd‡mi mxj †gvni) | O42: B-‡gBj | P42: . . . . . . . . . . . . . . . . . . .
F43: wVKvbv | G43: ='MisC Cal-1'!G146 -> 50/1, wfAvBwc †ivW, bqvcëb, XvKv| | O43: wVKvbv | P43: ='MisC Cal-1'!G146 -> 50/1, wfAvBwc †ivW, bqvcëb, XvKv|

Sheet 172,280 Notices
A2: RvZxq ivR¯^ †evW© www.nbr.gov.bd | I2: AvB.wU-10 (2023) | J2: RvZxq ivR¯^ †evW© www.nbr.gov.bd | R2: AvB.wU-124 (2023)
A5: AvqKi AvBb, 2023 Gi aviv 172 Abyhvqx †bvwUk | J5: AvqKi AvBb, 2023 Gi aviv 280 Abyhvqx †bvwUk
A6: (AvqKi Awdm) | J6: (AvqKi Awdm)
A8: bs t | B8: ="wit`vt/"&'Data Input'!F4&"/mv-"&'Data Input'!K4&"/"&'Data Input'!K25&"/" -> wit`vt/387493583464/mv-16/0/ | H8: ZvwiLt | I8: =TEXT('Data Input'!F5,"dd/mm/yyyy") -> 30/12/2026 | J8: bs t | K8: ="Rwigvbv/"&'Data Input'!F4&"/mv-"&'Data Input'!K4&"/"&'Data Input'!K25&"/" -> Rwigvbv/387493583464/mv-16/0/ | Q8: ZvwiLt | R8: =TEXT('Data Input'!F5,"dd/mm/yyyy") -> 30/12/2026
A9: cÖwZ | J9: cÖwZ | K9: .................................................................................
A11: Ki`vZvi bvgt | B11: ='Data Input'!D6 -> Rbve †gvt bvCg nvmvb | J11: Ki`vZvi bvgt | K11: ='Data Input'!D6 -> Rbve †gvt bvCg nvmvb
A12: wVKvbvt | B12: ='Data Input'!D7 | J12: wVKvbvt | K12: ='Data Input'!D7
A14: wUAvBGbt | B14: ='Data Input'!F4&"/Ktmvt-"&'Data Input'!K4 -> 387493583464/Ktmvt-16 | J14: wUAvBGbt | K14: ='Data Input'!F4&"/Ktmvt-"&'Data Input'!K4 -> 387493583464/Ktmvt-16
A15: Kiel©t | B15: ='Data Input'!D4 -> 2025-26 | J15: Kiel©t | K15: ='Data Input'!D4 -> 2025-26
A17: =" 1) GB Kvh©vj‡qi †iKW© †gvZv‡eK Avcwb/ Avcbvi "&B15&" Gi DwjøwLZ " -> 1) GB Kvh©vj‡qi †iKW© †gvZv‡eK Avcwb/ Avcbvi 2025-26 Gi DwjøwLZ | J17: AÎ Kvh©vj‡qi †iKW© †gvZv‡eK
A18: Kie‡l©i wiUvb© `vwLj K‡ib bvB ewjqv cÖZxqgvb nq|
A19: 2) AvqKi AvBb, 2023 Gi aviv 172 Gi kZ©vbymv‡i Avcbv‡K GZØviv DwjøwLZ Kie‡l©i mswkøó | J19: 1) Avcwb AvqKi AvBb, 2023 Gi aviv ................................ Abyhvqx
A20: Avqe‡l©i hveZxq Av‡qi weeiY I mswkøó Ab¨vb¨ Z_¨vw`mn AvqKi wiUvb© dig c~iY Kwiqv | J20: K) AvqKi wiUvb©/Dr‡m K‡ii wiUvb© `vwLj Kwi‡Z e¨_© nBqv‡Qb;
A21: =" ¯^v¶ic~e©K Zvnv GB †bvwUk cÖvwßi 22 w`‡bi g‡a¨ A_ev "&TEXT((I8+22),"dd/mm/yyyy")&" Zvwi‡Li c~‡e© wbgœ¯^v¶iKvixi" -> #VALUE! | J21: L) mswkøó Kie‡l©i Rb¨ cÖ‡`q cÖZ¨qbcÎ/wee„wZ/wnmv‡ei LvZvcÎ A_ev Z_¨vw` `vwLj/wba©vwiZ c×wZ‡Z msiÿY Kwi‡Z e¨_©
A22: `ß‡i `vwLj Kwievi Rb¨ Aby‡iva Rvbv‡bv hvB‡Z‡Q| | J22: nBqv‡Qb;
A23: 3) wiUvb© dig RvZxq ivR¯^ †ev‡W©i I‡qemvBU www.nbr.gov.bd Ges †h †Kvb AvqKi Awdm nB‡Z | J23: M) mswkøó Kie‡l©i Rb¨ AwMÖg Ki cÖ`v‡b e¨_© nBqv‡Qb/AwMÖg K‡ii AmZ¨ cÖv°jb Dc¯’vcb Kwiqv‡Qb;
A24: msMÖn Kiv hvB‡e| wiUvb© dig c~iY Kwievi wbqgvejx D³ di‡gB D‡jøL iwnqv‡Q| | J24: N) mswkøó Kie‡l©i Rb¨ †cÖwiZ ‡bvwU‡ki kZ© cwicvjb Kwi‡Z e¨_© nBqv‡Qb/†bvwUk Agvb¨ Kwiqv‡Qb;
A25: 4) GB †bvwUk Abymv‡i wiUvb© `vwL‡j e¨_© nB‡j AvqKi AvBb, 2023 Gi aviv 184 Abyhvqx | J25: O) mswkøó Kie‡l©i Rb¨ wiUv‡b©i wfwË‡Z cÖ‡`q Ki cwi‡kva Kwi‡Z e¨_© nBqv‡Qb;
A26: GKZidvfv‡e Ki wba©viY Kivi eva¨evaKZv iwnqv‡Q| Zvnv Qvov D³ AvB‡bi aviv 266 Abyhvqx | J26: P) mswkøó Kie‡l©i Rb¨ cÖ‡`q As‡Ki Ki cwi‡kva GovBqv wMqv‡Qb/dvuwK w`qv‡Qb;
A27: Rwigvbv Av‡iv‡ci weavb iwnqv‡Q| | J27: Q) Avgm© †js_ cÖvBm cwiMYbvi weavb cwicvjb Kwi‡Z e¨_© nBqv‡Qb;
J28: R) AvšÍR©vwZK †jb‡`‡bi †ÿ‡Î Z_¨, `wjjvw` I †iKW© msiÿY I iÿYv‡eÿY ev mieivn Kwi‡Z e¨_© nBqv‡Qb;
J29: S) AvšÍR©vwZK †jb‡`b m¤úwK©Z weeiYx/AvšÍR©vwZK †jb‡`b m¤úwK©Z PvU©vW© G¨vKvD‡›U›U nB‡Z cÖwZ‡e`b `vwL‡j e¨_© nBqv‡Qb;
J30: T).......................................................................... cwicvjb Kwi‡Z e¨_© nBqv‡Qb;
J31: U) Ab¨vb¨......................................................................................................|
H32: Dc Ki Kwgkbvi | J32: 2) Avcwb,
H33: (bvg, ¯^v¶i I mxj) | J33: K) Rvj (fake) wUAvBGb e¨envi Kwiqv‡Qb/Rvj wbixÿv cÖwZ‡e`b cÖYqb/`vwLj Kwiqv‡Qb;
J34: L) AmZ¨ A_ev Aï× wbixwÿZ wnmve weeiYx cÖbqb/`vwLj Kwiqv‡Qb/ PvU©vW© G¨vKvD‡›U›U KZ©„K IAS, IFRS I ISA
J35: AbymiY Kivi cÖZ¨qb Kiv nq bvB;
J36: M) Ki cwi‡kv‡a †Ljvcx nBqv‡Qb;
J37: N) Ab¨vb¨......................................................................................................|
J38: GZØviv Avcbv‡K AvqKi AvBb, 2023 Gi aviv ........... Abyhvqx †Kb Rwigvbv Av‡ivc Kiv nB‡e bv Zvnvi KviY
J39: ="`k©vB‡Z "&TEXT('MisC Intrst-3'!L26,"dd/mm/yyyy")&" ZvwiL 11:00 NwUKvq Avcbv‡K ¯^qs A_ev AvqKi AvBb, 2023 Gi aviv 327 Abyhvqx " -> `k©vB‡Z 21/01/2027 ZvwiL 11:00 NwUKvq Avcbv‡K ¯^qs A_ev AvqKi AvBb, 2023 Gi aviv 327 Abyhvqx
J40: wjwLZfv‡e ¶gZvcÖvß Aby‡gvw`Z cÖwZwbwa‡K wbæ¯^v¶iKvixi Awd‡m ïbvbx‡Z Dcw¯’Z nB‡Z Aby‡iva Kiv hvB‡Z‡Q|
G41: ='MisC Cal-1'!D146 -> †dvbt 02-2222244444
A42: (Awd‡mi mxj †gvni) | F42: B-‡gBj | G42: . . . . . . . . . . . . . . . . . . .
F43: wVKvbv | G43: ='MisC Cal-1'!G146 -> 50/1, wfAvBwc †ivW, bqvcëb, XvKv| | J43: (Awd‡mi mxj †gvni) | P43: Dc Ki Kwgkbvi
P44: (bvg, ¯^v¶i I mxj)

Sheet Min Tax
E3: Ki wba©viYx Av‡`‡ki †¶‡Î-
B5: b~¨bZg Ki cwiMYbvt-
B6: Ki`vZvi .................................................. e¨emvi †¶‡Î Dr‡m KwZ©Z Ki AvqKi AvBb, 2023 Gi 163 aviv Abyhvqx b~¨bZg Ki`vq we‡ewPZ nIqvq, Ki`vZvi †gvU Avq I Ki `v‡qi cwigvb wb¤œiæcfv‡e wbiƒcb Kiv nj-
B9: (K) wbqwgZ Dr‡mi Avq
B10: (¯’vbxq weµq+ Ab¨vb¨ m~‡Îi Avq) | G10: ="Uvt "&'Sheet of Calculation'!D24&"/-" -> Uvt 5462355/-
B12: wbqwgZ Dr‡mi Rb¨ Ki`vq | G12: ="Uvt "&'MisC Cal-1'!L8&"/-" -> Uvt 1203706.5/-
B13: (L) Avg`vbx I mievn e¨emv‡qi Rb¨ Ki`vqt
B14: wbqwgZ Dr‡mi Avq | G14: ="Uvt "&'Sheet of Calculation'!D24&"/-" -> Uvt 5462355/-
B15: 163 avivi Avq/e¨emvi Avq | G15: ="Uvt "&'Data Input'!E35&"/-" -> Uvt 1728142/-
B16: `ywU Dr‡mi Av‡qi ‡hvMdj | G16: ="Uvt "&'Sheet of Calculation'!D26&"/-" -> Uvt 7190497/-
B18: ='Sheet of Calculation'!D26&"/- UvKvi Dci cÖ‡hvR¨ nv‡i AvqKi:" -> 7190497/- UvKvi Dci cÖ‡hvR¨ nv‡i AvqKi: | G18: ="Uvt "&'MisC Cal-1'!G16&"/-" -> Uvt 1722149.1/-
B19: ev`t wbqwgZ Dr‡mi Av‡qi Dci cÖ‡hvR¨ AvqKi | G19: ="Uvt "&'MisC Cal-1'!L8&"/-" -> Uvt 1203706.5/-
B20: 163(2)/163(4) avivi b~¨bZg Ki`vq | G20: ="Uvt "&'MisC Cal-1'!G17&"/-" -> Uvt 518442.6/-
B21: Avg`vbx I mieivn e¨emv‡qi Rb¨-
B22: (1) 163(2)/163(4) avivi b~¨bZg Ki`vq | G22: ="Uvt "&'MisC Cal-1'!G17&"/-" -> Uvt 518442.6/-
B23: (2) 163(5) avivi Uvb©Ifvi U¨v· | G23: ="Uvt "&'MisC Cal-1'!I12&"/-" -> Uvt 175000/-
B24: (3) 163 avivq Dr‡m KwZ©Z b~¨bZg K‡ii cwigvY | G24: ="Uvt "&'Data Input'!F35&"/-" -> Uvt 180000/-
B26: =".................................................. e¨emvq 163(6) avivbymv‡i b¨~bZg Ki`vq "&'MisC Cal-1'!F18&" /- UvKv, hv (1), (2) I (3) Gi g‡a¨ m‡e©v”P|" -> .................................................. e¨emvq 163(6) avivbymv‡i b¨~bZg Ki`vq 518442.6 /- UvKv, hv (1), (2) I (3) Gi g‡a¨ m‡e©v”P|
B29: ="myZivs, "&'Data Input'!D4&" Ki eQ‡i Ki`vZvi †gvU Avq n‡e ( "&'Sheet of Calculation'!D24&"+"&'Data Input'!E35& ") = "&'Sheet of Calculation'!D26&"/- UvKv Ges Ki`vq n‡e ("&'MisC Cal-1'!L8&" + "&'MisC Cal-1'!F18&" ) = "&'MisC Cal-1'!E29&"/- UvKv| " -> myZivs, 2025-26 Ki eQ‡i Ki`vZvi †gvU Avq n‡e ( 5462355+1728142) = 7190497/- UvKv Ges Ki`vq n‡e (1203706.5 + 518442.6 ) = 1722149.1/- UvKv|

Sheet 212 Notice
A2: RvZxq ivR¯^ †evW© www.nbr.gov.bd | I2: AvB.wU-90 (2023)
A5: AvqKi AvBb, 2023 Gi aviv 212 Abyhvqx †bvwUk
A6: (AvqKi Awdm)
A8: bs t | B8: ="cytDt/"&'Data Input'!F4&"/mv-"&'Data Input'!K4&"/"&'Data Input'!K25&"/" -> cytDt/387493583464/mv-16/0/ | H8: ZvwiLt | I8: =TEXT('Data Input'!F5,"dd/mm/yyyy") -> 30/12/2026
A9: cÖwZ
A11: Ki`vZvi bvgt | B11: ='Data Input'!D6 -> Rbve †gvt bvCg nvmvb
A12: wVKvbvt | B12: ='Data Input'!D7
A14: wUAvBGbt | B14: ='Data Input'!F4&"/Ktmvt-"&'Data Input'!K4 -> 387493583464/Ktmvt-16
A15: Kiel©t | B15: ='Data Input'!D4 -> 2025-26
A17: wb¤œ¯^vÿiKvixi wek¦vm Kwievi KviY iwnqv‡Q †h, wb¤œewY©Z Dcv‡q Dchy©³ Ki`vZv KZ…©K aviv 212(9) Abyhvqx cÖ‡`q Ki
A18: I Ab¨vb¨ A¼ cwi‡kva GovBqv hvIqv nBqv‡Q:
A19: ........................................................................................................................
A20: ....1| cybt D‡b¥vP‡bi KviYmg~‡ni AewnZKiYcÎ mshy³| ...........................................
A21: ........................................................................................................................
A22: (cÖ‡hvR¨ †ÿ‡Î mshy³ cvZv `ªóe¨)|
A24: 2| d‡j GB †bvwUk cvBevi 22 (evBk) w`‡bi g‡a¨-
A25: =" (K) Ki`vZvi ..."&TEXT('MisC Intrst-3'!N4,"dd/mm/yyyy")&".... Zvwi‡L mgvß Avq e‡l©i AvqKi wiUvb© `vwLj Kwievi Rb¨;" -> (K) Ki`vZvi ...30/06/2025.... Zvwi‡L mgvß Avq e‡l©i AvqKi wiUvb© `vwLj Kwievi Rb¨;
A26: (L) cÖ‡`q †hB cwigvY Ki I Ab¨vb¨ A¼ cwi‡kva GovBqv hvIqv nBqv‡Q Zvnv ewY©Z AvqKi wiUvb© `vwLj Kwievi
A27: c~‡e© ev wiUvb© `vwLjKv‡j cwi‡kv‡ai Rb¨;
A28: (M) `vwLjK…Z wiUv‡Y© †h Bmy¨‡Z Ki cwi‡kva GovBqv wMqv‡Q Zv my¯úó D‡jø‡Li Rb¨;
A29: GB ‡bvwUk †cÖiY Kiv nBj|
A31: 3| Aby‡”Q` 2 G ewY©Z AvqKi wiUv‡b©i mwnZ mswkøó weeiYx I `wjjvw` `vwLj Kwi‡Z nB‡e|
A33: 4| GB †bvwUk Abymv‡i wiUvb© `vwL‡j e¨_© nB‡j AvqKi AvBb, 2023 Gi 183 ev 184 aviv Abyhvqx
A34: Ki wba©viY Kwievi weavb iwnqv‡Q| ZvnvQvov D³ AvB‡bi 266 aviv Abyhvqx Rwigvbv Ges
A35: 312 aviv Abyhvqx `Û Av‡iv‡ci weavb iwnqv‡Q|
H38: Dc Ki Kwgkbvi
H39: (bvg, ¯^v¶i I mxj)
G42: ='MisC Cal-1'!D146 -> †dvbt 02-2222244444
A43: (Awd‡mi mxj †gvni) | F43: B-‡gBj | G43: ...............................
F44: wVKvbv | G44: ='MisC Cal-1'!G146 -> 50/1, wfAvBwc †ivW, bqvcëb, XvKv|

Sheet MisC Cal-1
B2: 82C (Min Tax Calculation) | Z2: ='Data Input'!K5 -> খুলনা | AA2: ='Data Input'!I8 -> আয়কর কোম্পানী ব্যতীত | AB2: {=_xlfn.XLOOKUP(Z2,AA5:AA36,AB5:AD36,{2,3,4},FALSE)} -> 1-1141-0055-০১০১ | AC2: 1-1141-0055-0১১১ | AD2: 1-1141-0055-১৮৭৬ | AF2: =IF(AA2=AB4,AB2,IF(AA2=AC4,AC2,IF(AA2=AD4,AD2,0))) -> 1-1141-0055-0১১১ | AI2: c`ext | AJ2: ='Data Input'!F8 -> Individual | AK2: Trunover Tax
K3: BRTA Mvwoi U¨v· wn‡m‡e aviYvMZ AvqKi | AA3: Ki AÂjwfwËK †KvW | AI3: Individual | AJ3: Individual | AK3: =IF(I7>0,I7,0) -> 175000 | AL3: =_xlfn.XLOOKUP(AJ2,AI3:AI38,AJ3:AJ38,0,1) -> Individual | AM3: Trunover Tax
B4: ‡gvU Avq (163 Avq e¨wZZ) | D4: ='Sheet of Calculation'!D24 -> 5462355 | E4: ='Sheet of Calculation'!E24 -> 84000 | H4: Tax Rate | I4: 0.0025 | K4: *153(6) avivbymv‡i Mvwoi U¨v· we‡ePbvq aviYvMZ | AA4: কর অঞ্চল | AB4: আয়কর কোম্পানীসমূহ | AC4: আয়কর কোম্পানী ব্যতীত | AD4: অন্যান্য ফি সমূহ | AI4: Govt. Employee | AJ4: Individual | AK4: =IF(AK3>0,AM3,AM4) -> Trunover Tax | AL4: -- | AM4: Trunover Tax (N/A)
B5: 163 avivq Avq | D5: ='Sheet of Calculation'!D25 -> 1728142 | E5: ='Data Input'!F35 -> 180000 | F5: (b¨~bZg Ki`vq) | I5: 0.006 | K5: =IF(L7>L6,K4,L5) -> 0 | L5: 0 | AA5: ১, ঢাকা | AB5: 1-1141-০০০১-০১০১ | AC5: ১-১১৪১-০০০১-০১১১ | AD5: ১-১১৪১-০০০১-১৮৭৬ | AI5: Pvt. Employee | AJ5: Individual
B6: ‡gvU Avq (163 b¨~bZg Ki`vqfz³ Avq mn) | D6: ='Sheet of Calculation'!D26 -> 7190497 | H6: Gross Receipt/Sales: | I6: ='Data Input'!F9 -> 70000000 | K6: cÖK…Z AvqKi (wbqwgZ Dr‡mi Avq n‡Z) | L6: =F17 -> 1203706.5 | AA6: ২, ঢাকা | AB6: 1-1141-0005-০১০১ | AC6: 1-1141-0005-0111 | AD6: ১-১১৪১-০০০৫-১৮৭৬ | AI6: Others (individual) | AJ6: Individual | AK6: Individual | AL6: 30000000 | AM6: =IF(I6>=AL6,I6*I4,0) -> 175000
B7: 163 avivq Avq (mÂqc‡Îi gybvdv BZ¨vw`) | D7: ='Sheet of Calculation'!D27 -> 0 | E7: ='Sheet of Calculation'!E27 -> 0 | F7: (P‚ovšÍ Ki`vqfz³) | H7: =AK4 -> Trunover Tax | I7: =_xlfn.XLOOKUP(AL3,AK6:AK9,AM6:AM9,0,1) -> 175000 | K7: ='Data Input'!D45 -> 153 avivq Mvwoi AwMÖg AvqKi | L7: ='Data Input'!E45 -> 75000 | AA7: ৩, ঢাকা | AB7: 1-1141-0010-০১০১ | AC7: ১-১১৪১-০০১০-০১১১ | AD7: 1-1141-0010-১৮৭৬ | AI7: Firm | AJ7: Firm/AOP/Simillar | AK7: Firm/AOP/Simillar | AL7: 5000000 | AM7: =IF(I6>=AL7,I6*I5,0) -> 420000
K8: aviYvMZ AvqKi (wbqwgZ Dr‡mi) | L8: =IF(L7>L6,L7,L6) -> 1203706.5 | AA8: ৪, ঢাকা | AB8: 1-1141-0015-০১০১ | AC8: 1-1141-0015-০১১১ | AD8: 1-1141-0015-18৭৬ | AI8: AOP | AJ8: Firm/AOP/Simillar | AK8: Company | AL8: 0 | AM8: =IF(I6>=AL8,I6*I5,0) -> 420000
B9: Ki cwiMYbv | D9: avc | E9: nvi | F9: UvKv | AA9: ৫, ঢাকা | AB9: ১-১১৪১-০০২০-০১০১ | AC9: 1-1141-0020-0111 | AD9: 1-1141-0020-1876 | AI9: Trust | AJ9: Firm/AOP/Simillar | AK9: Others | AL9: =AL7 -> 5000000 | AM9: =IF(I6>=AL9,I6*I5,0) -> 420000
C10: =D6 -> 7190497 | D10: ='MisC Cal-1'!D67 -> 350000 | E10: ='MisC Cal-1'!E67 -> 0 | F10: =MIN(C10:D10)*E10 -> 0 | H10: b¨~bZg Ki cwi‡kva | I10: ='Data Input'!F35 -> 180000 | AA10: ৬, ঢাকা | AB10: 1-1141-0025-০১০১ | AC10: 1-1141-0025-0111 | AD10: 1-1141-0025-187৬ | AI10: N.G.O. | AJ10: Company
C11: =IF(C10>D10,(C10-D10),0) -> 6840497 | D11: ='MisC Cal-1'!D68 -> 100000 | E11: ='MisC Cal-1'!E68 -> 0.05 | F11: =MIN(C11:D11)*E11 -> 5000 | H11: U/S 163(2),(4) Tax | I11: =G17 -> 518442.6 | AA11: ৭, ঢাকা | AB11: 1-1141-0030-০১০১ | AC11: 1-1141-0030-০১১১ | AD11: ১-১১৪১-০০৩০-১৮৭৬ | AI11: Company | AJ11: Company
C12: =IF(C11>D11,(C11-D11),0) -> 6740497 | D12: ='MisC Cal-1'!D69 -> 400000 | E12: ='MisC Cal-1'!E69 -> 0.1 | F12: =MIN(C12:D12)*E12 -> 40000 | H12: =H7 -> Trunover Tax | I12: =I7 -> 175000 | K12: BRTA গাড়ির ট্যাক্স অফেরতযোগ্য | AA12: ৮, ঢাকা | AB12: 1-1141-0035-০১০১ | AC12: 1-1141-0035-০১১১ | AD12: 1-1141-0035-১৮৭৬ | AI12: - | AJ12: Individual
C13: =IF(C12>D12,(C12-D12),0) -> 6340497 | D13: ='MisC Cal-1'!D70 -> 500000 | E13: ='MisC Cal-1'!E70 -> 0.15 | F13: =MIN(C13:D13)*E13 -> 75000 | K13: 153(7) aviv we‡ePbvq | AA13: ৯, ঢাকা | AB13: 1-1141-008০-০১০১ | AC13: 1-1141-008০-০১১১ | AD13: 1-1141-008০-১৮৭৬ | AI13: Officer | AJ13: Individual
C14: =IF(C13>D13,(C13-D13),0) -> 5840497 | D14: ='MisC Cal-1'!D71 -> 500000 | E14: ='MisC Cal-1'!E71 -> 0.2 | F14: =MIN(C14:D14)*E14 -> 100000 | N14: cwi‡kvwaZ Kit | AA14: ১০, ঢাকা | AB14: 1-1141-0085-০১০১ | AC14: 1-1141-0085-0111 | AD14: 1-1141-0085-১৮৭৬ | AI14: Sr. Officer | AJ14: Individual
C15: =IF(C14>D14,(C14-D14),0) -> 5340497 | D15: ='MisC Cal-1'!D72 -> 2000000 | E15: ='MisC Cal-1'!E72 -> 0.25 | F15: =_xlfn.XLOOKUP('MisC Intrst-3'!L3,'MisC Intrst-3'!R10:R23,'MisC Intrst-3'!AR10:AR23,0) -> 500000 | G15: me©‡gvU Ki`vq | H15: b¨~bZg Ki cwi‡kva | K15: †iqvZ c~e©eZ©x AvqKi (wbqwgZ/aviYvMZ+ b¨~bZg) | L15: =L8+F18 -> 1722149.1 | N15: Dr‡m Ki (wbqwgZ) | O15: ='Data Input'!F33 -> 84000 | AA15: ১১, ঢাকা | AB15: 1-1141-0090-০১০১ | AC15: ১-১১৪১-০০৯০-০১১১ | AD15: 1-1141-009০-১৮৭৬ | AI15: Service Holder | AJ15: Individual
C16: =IF(C15>D15,(C15-D15),0) -> 3340497 | D16: ='MisC Cal-1'!D73 -> Aewkó | E16: ='MisC Cal-1'!E73 -> 0.3 | F16: =IF(C16>0,(C16*E16),0) -> 1002149.1 | G16: =SUM(F10:F16) -> 1722149.1 | H16: ='Data Input'!F35 -> 180000 | K16: Ki †iqvZ (ev`) | L16: ='MisC Cal-2'!D69 -> 258717.26 | N16: Dr‡m Ki (b¨~bZg I P‚ovšÍ) | O16: ='Data Input'!F35+'Data Input'!F37 -> 180000 | AA16: ১২, ঢাকা | AB16: 1-1141-0095-০১০১ | AC16: 1-1141-0095-01১১ | AD16: 1-1141-0095-১৮৭৬ | AI16: Bussiness Person | AJ16: Individual
B17: cÖK…Z AvqKi (wbqwgZ Dr‡mi Avq n‡Z) | F17: =SUM('Sheet of Calculation'!F30:F36) -> 1203706.5 | G17: =IF((G16-F17)<0,0,(G16-F17)) -> 518442.6 | K17: †iqvZ cieZ©x (wbqwgZ/aviYvMZ+AwZt b¨~bZg Ki`vq) | L17: =E34-H16 -> 1283431.8 | N17: 152/154 AwMÖg Ki | O17: ='Data Input'!E44 -> 400000 | AA17: ১৩, ঢাকা | AB17: 1-1141-01০০-০১০১ | AC17: 1-1141-0100-01১১ | AD17: 1-1141-0100-১৮৭৬ | AI17: Tax Payee (General) | AJ17: Individual
B18: 163 avivbymv‡i AvqKi (cÖK…Z b¨~bZg Ki`vq) | F18: =MAX(I10:I12) -> 518442.6 | K18: ‡gvU AvqKi (mviPvR© mn) | L18: =L17+'MisC Cal-2'!D10 -> 1283431.8 | N18: wiUv‡b©i mv‡_ 173 | O18: ='Data Input'!E46 -> 0 | AA18: ১৪, ঢাকা | AB18: 1-1141-0105-0১০১ | AC18: 1-1141-0105-0১১১ | AD18: 1-1141-0105-১৮৭৬ | AI18: Banker (Govt) | AJ18: Individual
B19: 163 avivq P‚ovšÍ Ki`vqmg~n (mÂqc‡Îi gybvdv BZ¨vw`) | F19: ='Data Input'!F37 -> 0 | K19: 153 avivq Mvwoi AvqKi | L19: ='Data Input'!E45 -> 75000 | N19: cwi‡kvwaZ †gvUt | O19: =SUM(O15:O18) -> 664000 | AA19: ১৫, ঢাকা | AB19: 1-1141-0110-০১০১ | AC19: ১-১১৪১-০১১০-০১১১ | AD19: 1-1141-0110-18৭৬ | AI19: Banker (Non-Executive) | AJ19: Individual
B20: †iqvZ c~e©eZ©x cÖK…Z AvqKi (wbqwgZ I b¨~bZg/P‚ovšÍ Ki`vq) | F20: =SUM(F17:F19) -> 1722149.1 | K20: Aewkó Ki`vq | L20: =L18-L19 -> 1208431.8 | AA20: ১, চট্টগ্রাম | AB20: 1-1141-0040-০১০১ | AC20: ১-১১৪১-০০৪০-০১১১ | AD20: ১-১১৪১-০০৪০-১৮৭৬ | AI20: Banker (Executive) | AJ20: Individual
K21: Mvwoi U¨v· A‡diZ‡hvM¨ we‡ePbvq, Aewkó Ki`vq | L21: =IF(L20>=0,L20,0) -> 1208431.8 | AA21: ২, চট্টগ্রাম | AB21: 1-1141-0045-০১০১ | AC21: 1-1141-0045-০১১১ | AD21: 1-1141-0045-১৮৭৬ | AI21: A.G.M/D.G.M | AJ21: Individual
K22: Aewkó Ki`vq + cwi‡kvwaZ (b¨~bZg+ P‚ovšÍ) Ki`vq | L22: =L21+H16+F19 -> 1388431.8 | AA22: ৩,চট্টগ্রাম | AB22: 1-1141-0050-০১০১ | AC22: ১-১১৪১-০০৫০-০১১১ | AD22: ১-১১৪১-০০৫০-১৮৭৬ | AI22: G.M/D.M.D | AJ22: Individual
K23: bxU AvqKi | L23: =L22-O19 -> 724431.84 | AA23: ৪, চট্টগ্রাম | AB23: 1-1141-0135-০১০১ | AC23: 1-1141-0135-01১১ | AD23: 1-1141-0135-১৮৭৬ | AI23: MD/CEO | AJ23: Individual
AA24: খুলনা | AB24: 1-1141-0055-০১০১ | AC24: 1-1141-0055-0১১১ | AD24: 1-1141-0055-১৮৭৬ | AI24: Director/Equivalent | AJ24: Individual
B25: b¨~bZg Ki`vq A‡diZ‡hvM¨ , Amgš^q‡hvM¨ Ges 100% cwi‡kva‡hvM¨ | AA25: রাজশাহী | AB25: 1-1141-0060-০১০১ | AC25: ১-১১৪১-০০৬০-০১১১ | AD25: ১-১১৪১-০০৬০-১৮৭৬ | AI25: Manager/Equivalent | AJ25: Individual
AA26: রংপুর | AB26: 1-1141-0065-০১০১ | AC26: 1-1141-0065-০১১১ | AD26: 1-1141-0065-১৮৭৬ | AI26: Ret. Officials | AJ26: Individual
B27: ‡gvU Avq (wbqwgZ+ b¨~bZg) | E27: ='Data Input'!E36 -> 7190497 | AA27: সিলেট | AB27: ১-১১৪১-০০৭০-০১০১ | AC27: ১-১১৪১-০০৭০-০১১১ | AD27: ১-১১৪১-০০৭০-১৮৭৬ | AI27: Funds | AJ27: Firm/AOP/Simillar
B28: Ki cwiMYbvi cÖ_g avct | E28: ='Sheet of Calculation'!D30 -> 350000 | AA28: বরিশাল | AB28: 1-1141-0075-০১০১ | AC28: 1-1141-0075-01১১ | AD28: 1-1141-0075-১৮৭৬ | AI28: AJP (previous) | AJ28: Others
B29: †iqvZ c~e©eZ©x AvqKi (wbqwgZ/aviYvMZ+ b¨~bZg) | E29: =L8+F18 -> 1722149.1 | AA29: গাজীপুর | AB29: 1-1141-0120-0১০১ | AC29: 1-1141-0120-0111 | AD29: 1-1141-0120-18৭৬৬ | AI29: Hindu Undivided Family | AJ29: Firm/AOP/Simillar
B30: Ki †iqvZ (ev`) | E30: ='MisC Cal-2'!D69 -> 258717.26 | AA30: নারায়ণগঞ্জ | AB30: 1-1141-0115-0101 | AC30: 1-1141-0115-01১১ | AD30: 1-1141-0115-১৮৭৬ | AI30: AOB | AJ30: Firm/AOP/Simillar
B31: †iqvZ cieZ©x AvqKi (wbqwgZ/aviYvMZ+ b¨~bZg) | E31: =F18+E41 -> 1463431.8 | F31: 3000 | AA31: বগুড়া | AB31: 1-1141-0140-0101 | AC31: ১-১১৪১-০১৪০-০১১১ | AD31: 1-1141-0140-১৮৭৬ | AI31: Insurance | AJ31: Company
B32: b¨~bZg Ki`vq (GjvKv wfwËK) | E32: ='Data Input'!I6 -> 4000 | F32: 4000 | AA32: কুমিল্লা | AB32: 1-1141-0130-০১০১ | AC32: 1-1141-0130-01১১ | AD32: 1-1141-0130-১৮৭৬ | AI32: Local Authority | AJ32: Company
B33: †iqvZ cieZ©x (GjvKv wfwËK) b¨~bZg Ki`vq | E33: =IF(E27>E28,MAX(E31:E32),E31) -> 1463431.8 | F33: 5000 | AA33: ময়মনসিংহ | AB33: 1-1141-0125-0১০১ | AC33: 1-1141-0125-0111 | AD33: 1-1141-0125-1৮৭৬ | AI33: Educational Institution | AJ33: Others
B34: †iqvZ cieZ©x ‡gvU AvqKi/b¨~bZg Ki`vq | E34: =IF(E33>='Data Input'!I6,'MisC Cal-1'!E33,0) -> 1463431.8 | AA34: বৃহৎ করদাতা ইউনিট | AB34: ১-১১৪৫-০০১০-০১০১ | AC34: 1-1145-0010-0111 | AD34: 1-1145-0010-18৭৬ | AI34: Society/Co-Operative S. | AJ34: Company
B35: †iqvZ cieZ©x AvqKi (wbqwgZ/aviYvMZ+ b¨~bZg+P‚ovšÍ) | E35: =E34+F19 -> 1463431.8 | AA35: কেন্দ্রীয় জরীপ অঞ্চল | AB35: ১-১১৪৫-০০০৫-০১০১ | AC35: 1-1145-0005-01১১ | AD35: ১-১১৪৫-০০০৫-১৮৭৬ | AI35: MPO Schools | AJ35: Others
AA36: ট্যাক্সেস আপীলাত ট্রাইব্যুনাল | AB36: - | AC36: - | AD36: 1-1143-0015-১৮৭৬ | AI36: Govt. Universities | AJ36: Company
AA37: সি আই সি | AB37: - | AC37: - | AD37: - | AI37: Govt/Autonomous Org | AJ37: Company
B38: cÖK…Z AvqKi (wbqwgZ Dr‡mi Avq n‡Z) | E38: =L8 -> 1203706.5 | AA38: কর পরিদর্শন পরিদপ্তর, ঢাকা | AB38: - | AC38: - | AD38: - | AI38: Business Institutions/Org. | AJ38: Firm/AOP/Simillar
B39: *wbqwgZ Ki`v‡qi mv‡_ mgš^q‡hvM¨ Ki †iqvZ | E39: ='MisC Cal-2'!D69 -> 258717.26 | AA39: বিসিএস (কর) একাডেমী, ঢাকা | AB39: - | AC39: - | AD39: -
D40: cv_©K¨ | E40: =E38-E39 -> 944989.24 | AA40: জাতীয় রাজস্ব বোর্ড | AB40: - | AC40: - | AD40: -
B41: †iqvZ cieZ©x wbqwgZ Ki`vq (> 0) | E41: =IF(E40>=0,E40,0) -> 944989.24
Z42: Avwcj †iÄ | AA42: কর আপিল অঞ্চল | AD42: অন্যান্য ফি সমূহ
Z43: 1 | AA43: ১, ঢাকা | AD43: ১-১১৪৩-০০০১-১৮৭৬
Z44: 2 | AA44: ২, ঢাকা | AD44: ১-১১৪৩-০০০৫-১৮৭৬
Z45: 3 | AA45: ৩, ঢাকা | AD45: 1-1143-0010-১৮৭৬
Z46: 4 | AA46: ৪, ঢাকা | AD46: 1-1143-0035-1876
AA47: রাজশাহী | AD47: ১-১১৪৩-০০৪0-1876
AA48: খুলনা
AA49: চট্টগ্রাম
B54: ='Data Input'!D8 -> পুরুষ | C54: {=_xlfn.XLOOKUP(B54,B57:B64,C57:P64,{2,3,4,5,6,7,8,9,10,11,12,13,14},FALSE)} -> 250000 | D54: 250000 | E54: 250000 | F54: 250000 | G54: 300000 | H54: 300000 | I54: 300000 | J54: 350000 | K54: 350000 | L54: 350000 | M54: 375000 | N54: 375000 | O54: 375000 | P54: 375000
B56: aiY: | C56: 2016-17 | D56: 2017-18 | E56: 2018-19 | F56: 2019-20 | G56: 2020-21 | H56: 2021-22 | I56: 2022-2023 | J56: 2023-24 | K56: 2024-25 | L56: 2025-26 | M56: 2026-27 | N56: 2027-28 | O56: 2028-29 | P56: 2029-30
B57: পুরুষ | C57: 250000 | D57: 250000 | E57: 250000 | F57: 250000 | G57: 300000 | H57: 300000 | I57: 300000 | J57: 350000 | K57: 350000 | L57: 350000 | M57: 375000 | N57: 375000 | O57: 375000 | P57: 375000
B58: মহিলা | C58: 300000 | D58: 300000 | E58: 300000 | F58: 300000 | G58: 350000 | H58: 350000 | I58: 350000 | J58: 400000 | K58: 400000 | L58: 400000 | M58: 425000 | N58: 425000 | O58: 425000 | P58: 425000
B59: তৃতীয় লিঙ্গ | C59: 250000 | D59: 250000 | E59: 250000 | F59: 250000 | G59: 300000 | H59: 350000 | I59: 350000 | J59: 475000 | K59: 475000 | L59: 475000 | M59: 500000 | N59: 500000 | O59: 500000 | P59: 500000
B60: ৬৫ বা তদুর্ধ্ব বয়সী | C60: 300000 | D60: 300000 | E60: 300000 | F60: 300000 | G60: 350000 | H60: 350000 | I60: 350000 | J60: 400000 | K60: 400000 | L60: 400000 | M60: 425000 | N60: 425000 | O60: 425000 | P60: 425000
B61: প্রতিবন্ধী | C61: 375000 | D61: 400000 | E61: 400000 | F61: 400000 | G61: 450000 | H61: 450000 | I61: 450000 | J61: 475000 | K61: 475000 | L61: 475000 | M61: 500000 | N61: 500000 | O61: 500000 | P61: 500000
B62: যুদ্ধাহত মুক্তিযোদ্ধা/সমমান | C62: 425000 | D62: 425000 | E62: 425000 | F62: 425000 | G62: 475000 | H62: 475000 | I62: 475000 | J62: 500000 | K62: 500000 | L62: 500000 | M62: 525000 | N62: 525000 | O62: 525000 | P62: 525000
B63: প্রতিবন্ধী সন্তানযুক্ত পিতা | C63: 275000 | D63: 275000 | E63: 300000 | F63: 300000 | G63: 350000 | H63: 350000 | I63: 350000 | J63: =J57+50000 -> 400000 | K63: =K57+50000 -> 400000 | L63: =L57+50000 -> 400000 | M63: =M57+50000 -> 425000 | N63: =N57+50000 -> 425000 | O63: =O57+50000 -> 425000 | P63: =P57+50000 -> 425000
B64: প্রতিবন্ধী সন্তানযুক্ত মাতা | C64: 325000 | D64: 325000 | E64: 350000 | F64: 350000 | G64: 400000 | H64: 400000 | I64: 400000 | J64: =J58+50000 -> 450000 | K64: =K58+50000 -> 450000 | L64: =L58+50000 -> 450000 | M64: =M58+50000 -> 475000 | N64: =N58+50000 -> 475000 | O64: =O58+50000 -> 475000 | P64: =P58+50000 -> 475000
D66: avc | E66: nvi
A67: aiY: | B67: ='Data Input'!D4 -> 2025-26 | C67: ='Data Input'!D8 -> পুরুষ | D67: =_xlfn.XLOOKUP('MisC Intrst-3'!L3,'MisC Intrst-3'!R10:R23,'MisC Intrst-3'!Z10:Z23,0) -> 350000 | E67: 0
D68: =_xlfn.XLOOKUP('MisC Intrst-3'!L3,'MisC Intrst-3'!R10:R23,'MisC Intrst-3'!AA10:AA23,0) -> 100000 | E68: =_xlfn.XLOOKUP('MisC Intrst-3'!L3,'MisC Intrst-3'!R10:R23,'MisC Intrst-3'!AB10:AB23,0) -> 0.05
D69: =_xlfn.XLOOKUP('MisC Intrst-3'!L3,'MisC Intrst-3'!R10:R23,'MisC Intrst-3'!AC10:AC23,0) -> 400000 | E69: =(E68+5%) -> 0.1
D70: =_xlfn.XLOOKUP('MisC Intrst-3'!L3,'MisC Intrst-3'!R10:R23,'MisC Intrst-3'!AD10:AD23,0) -> 500000 | E70: =(E69+5%) -> 0.15
D71: =_xlfn.XLOOKUP('MisC Intrst-3'!L3,'MisC Intrst-3'!R10:R23,'MisC Intrst-3'!AE10:AE23,0) -> 500000 | E71: =(E70+5%) -> 0.2
D72: =_xlfn.XLOOKUP('MisC Intrst-3'!L3,'MisC Intrst-3'!R10:R23,'MisC Intrst-3'!AP10:AP23,0) -> 2000000 | E72: =(E71+5%) -> 0.25
D73: =IF('Sheet of Calculation'!B2='MisC Intrst-3'!R19," Aewkó ",0) -> Aewkó | E73: =IF('Sheet of Calculation'!B2='MisC Intrst-3'!R19,(E72+5%),"-") -> 0.3
H79: U/S 174
H81: Salary
B82: যাতায়াত ভাতা | D82: ='Data Input'!F11 -> বেতন-ভাতা (Yes) | E82: ='Data Input'!D14 -> †emiKvwi PvKwi n‡Z Avq (‡eZb I fvZvw`) | G82: Input | H82: Input | I82: cÖ`wk©Z/cÖK…Z Avq | J82: Ki-Ae¨vnwZ cÖvß Avq | K82: PvKwi n‡Z bxU Ki‡hvM¨ Avq
B83: মোটরগাড়ি প্রতি সুবিধা | D83: বেতন-ভাতা (Yes) | E83: ='Sheet of Calculation'!B7 -> মূল বেতন/মজুরি/পারিশ্রমিক ইত্যাদি | G83: =IF('Data Input'!E15<0,0,'Data Input'!E15) -> 1600000 | H83: =IF('Data Input'!F15<0,0,'Data Input'!F15) -> 0 | I83: =IF($D$82=$D$83,G83,$D$85) -> 1600000 | J83: =IF(H83>G83,0,(IF($D$82=$D$83,H83,$D$85))) -> 0 | K83: =IF((I83-J83)<=0,0,(I83-J83)) -> 1600000
B84: গাড়ি রক্ষণাবেক্ষণ ভাতা | D84: বেতন অপ্রযোজ্য | E84: ='Sheet of Calculation'!B8 -> মোটরগাড়ি প্রতি সুবিধা | G84: =IF('Data Input'!E16<0,0,'Data Input'!E16) -> 0 | H84: =IF('Data Input'!F16<0,0,'Data Input'!F16) -> 0 | I84: =IF($D$82=$D$83,G84,$D$85) -> 0 | J84: =IF(H84>G84,0,IF($D$82=$D$83,H84,$D$85)) -> 0 | K84: =IF((I84-J84)<=0,0,(I84-J84)) -> 0
B85: (ব্যক্তিগত ব্যবহারে) গাড়ির সুবিধা ভাতা | D85: 0 | E85: ='Sheet of Calculation'!B9 -> বাড়ি ভাড়া ভাতা | G85: =IF('Data Input'!E17<0,0,'Data Input'!E17) -> 0 | H85: =IF('Data Input'!F17<0,0,'Data Input'!F17) -> 0 | I85: =IF($D$82=$D$83,G85,$D$85) -> 0 | J85: =IF(H85>G85,0,IF($D$82=$D$83,H85,$D$85)) -> 0 | K85: =IF((I85-J85)<=0,0,(I85-J85)) -> 0
B86: অতিরিক্ত যাতায়াত ভাতা | C86: Salary | D86: =_xlfn.XLOOKUP(H92,'MisC Intrst-3'!R10:R23,'MisC Intrst-3'!AL10:AL23,0,1) -> No | E86: ='Sheet of Calculation'!B10 -> চিকিৎসা ভাতা/পারকুইজিট ইত্যাদি | G86: =IF('Data Input'!E18<0,0,'Data Input'!E18) -> 0 | H86: =IF('Data Input'!F18<0,0,'Data Input'!F18) -> 0 | I86: =IF($D$82=$D$83,G86,$D$85) -> 0 | J86: =IF(H86>G86,0,IF($D$82=$D$83,H86,$D$85)) -> 0 | K86: =IF((I86-J86)<=0,0,(I86-J86)) -> 0
C87: 174 Apply | D87: ='MisC Cal-2'!H82 -> 0 | E87: ='Sheet of Calculation'!B11 -> উৎসব/উৎসাহ বোনাস/অন্যান্য ইত্যাদি | G87: =IF('Data Input'!E19<0,0,'Data Input'!E19) -> 0 | H87: =IF('Data Input'!F19<0,0,'Data Input'!F19) -> 0 | I87: =IF($D$82=$D$83,G87,$D$85) -> 0 | J87: =IF(H87>G87,0,IF($D$82=$D$83,H87,$D$85)) -> 0 | K87: =IF((I87-J87)<=0,0,(I87-J87)) -> 0
E88: ='Sheet of Calculation'!B12 -> সম্পূর্ণ করযোগ্য ভাতা/ভাতা সমূহ | G88: =IF('Data Input'!E20<0,0,'Data Input'!E20) -> 0 | H88: =IF('Data Input'!F20<0,0,'Data Input'!F20) -> 0 | I88: =IF($D$82=$D$83,G88,$D$85) -> 0 | J88: =IF(H88>G88,0,IF($D$82=$D$83,H88,$D$85)) -> 0 | K88: =IF((I88-J88)<=0,0,(I88-J88)) -> 0
B89: মূল বেতন/মজুরি/পারিশ্রমিক ইত্যাদি | E89: ='Sheet of Calculation'!B13 -> আনুতোষিক/অ্যানুইটি, পেনশন বা ইহাদের সম্পূরক (করমুক্ত) | G89: =IF('Data Input'!E21<0,0,'Data Input'!E21) -> 0 | H89: =IF('Data Input'!F21<0,0,'Data Input'!F21) -> 0 | I89: =IF($D$82=$D$83,G89,$D$85) -> 0 | J89: =IF($D$82=$D$83,H89,$D$85) -> 0 | K89: =IF((I89-J89)<=0,0,(I89-J89)) -> 0
B90: বকেয়া বেতন/অগ্রিম বেতন, ইত্যাদি | E90: †gvU Avq = | G90: =SUM(G83:G89) -> 1600000 | H90: =SUM(H83:H89) -> 0 | I90: =SUM(I83:I89) -> 1600000 | J90: =SUM(J83:J89) -> 0 | K90: =SUM(K83:K89) -> 1600000
B91: বেতন/মজুরির পরিবর্তে প্রাপ্তি, ইত্যাদি
B92: বেতন (মূল/বকেয়া/অগ্রিম/অন্যান্য) | H92: ='Data Input'!D4 -> 2025-26 | I92: {=_xlfn.XLOOKUP('MisC Cal-2'!G4,_xlfn.ANCHORARRAY('MisC Cal-2'!I60),'MisC Cal-2'!I71:V71,0,1)} -> 1600000 | J92: {=_xlfn.XLOOKUP('MisC Cal-2'!G4,_xlfn.ANCHORARRAY('MisC Cal-2'!I60),'MisC Cal-2'!I72:V72,0,1)} -> 500000 | K92: {=_xlfn.XLOOKUP('MisC Cal-2'!G4,_xlfn.ANCHORARRAY('MisC Cal-2'!I60),'MisC Cal-2'!I73:V73,0,1)} -> 1100000
H94: if U/S 174 aply | I94: {=_xlfn.XLOOKUP('MisC Cal-2'!G4,_xlfn.ANCHORARRAY('MisC Cal-2'!I60),'MisC Cal-2'!I79:V79,0,1)} -> 1600000 | J94: {=_xlfn.XLOOKUP('MisC Cal-2'!G4,_xlfn.ANCHORARRAY('MisC Cal-2'!I60),'MisC Cal-2'!I80:V80,0,1)} -> 500000 | K94: {=_xlfn.XLOOKUP('MisC Cal-2'!G4,_xlfn.ANCHORARRAY('MisC Cal-2'!I60),'MisC Cal-2'!I81:V81,0,1)} -> 1100000
B95: বাড়ি ভাড়া ভাতা
B96: আবাসন সুবিধা | C96: (33 avivi Avq)
B98: চিকিৎসা ভাতা/পারকুইজিট ইত্যাদি
B99: উৎসব বোনাস, ইত্যাদি
B100: উৎসাহ বোনাস/ ইনসেনটিভস ইত্যাদি
B101: নববর্ষ ভাতা, শ্রান্তি বিনোদন/অন্যান্য ভাতা
B102: ছুটি ভাতা/ছুটি নগদায়ন ইত্যাদি
B103: উৎসব/উৎসাহ বোনাস/অন্যান্য ইত্যাদি
B104: সম্পূর্ণ করযোগ্য ভাতা/ভাতা সমূহ
B105: অন্য কোন পারকুইজিট/ভাতা/সুবিধা ইত্যাদি
B106: ওভারটাইম/কমিশন/অন্য কোন পারকুইজিট | C106: (34 avivi Avq)
B107: কর্মচারী শেয়ার স্কিম হতে আয়
B108: ভ্রমণ ভাতা (দেশে/বিদেশে)
B109: আপ্যায়ন ভাতা, ইত্যাদি
B110: অন্যান্য আর্থিক সুবিধা/ভাতা সমূহ ইত্যাদি
B111: অনুমোদিত ভবিষ্য তহবিলে নিয়োগকর্তা প্রদত্ত চাঁদা
B112: আনুতোষিক/অ্যানুইটি, পেনশন বা ইহাদের সম্পূরক
B115: স্বীকৃত ভবিষ্য তহবিলের সুদ (জিপিএফ ইত্যাদি)
B116: পুরষ্কার/নগদ প্রাপ্তি/সমমান সুবিধাদি (করমুক্ত)
B117: আনুতোষিক/অ্যানুইটি, পেনশন বা ইহাদের সম্পূরক (করমুক্ত)
...

Sheet MisC Cal-2
C4: mviPvR© | E4: Rate | F4: Min Surcharge | G4: ='Data Input'!D4 -> 2025-26 | I4: {=TRANSPOSE('MisC Intrst-3'!R10:R23)} -> 2016-17 | J4: 2017-18 | K4: 2018-19 | L4: 2019-20 | M4: 2020-21 | N4: 2021-22 | O4: 2022-23 | P4: 2023-24 | Q4: 2024-25 | R4: 2025-26 | S4: 2026-27 | T4: 2027-28 | U4: 2028-29 | V4: 2029-30
C5: =IF(E13=1,D13,D14) -> 8000 et dzt evwo/GKvwaK Mvwo | D5: ='Data Input'!D11 -> প্রযোজ্য নহে | E5: {=_xlfn.XLOOKUP(G4,I4:V4,I12:V17,0,1)} -> 0 | F5: {=_xlfn.XLOOKUP(G4,I4:V4,I19:V24,0,1)} -> 0 | G5: {=_xlfn.XLOOKUP(G4,I4:V4,I5:V10,0,1)} -> <= ৪ কোটি | I5: <= ২.২৫ কোটি | J5: <= ২.২৫ কোটি | K5: <= ২.২৫ কোটি | L5: <= ৩ কোটি | M5: <= ৩ কোটি | N5: <= ৩ কোটি | O5: <= ৩ কোটি | P5: <= ৪ কোটি | Q5: <= ৪ কোটি | R5: <= ৪ কোটি | S5: <= ৪ কোটি | T5: <= ৪ কোটি | U5: <= ৪ কোটি | V5: <= ৪ কোটি
C6: A_©eQi †k‡l bxU m¤c` | D6: ='Data Input'!D10 -> <= ৪ কোটি | E6: 0.1 | F6: 146343.18 | G6: ৪ ~ ১০ কোটি | I6: ২.২৫ ~ ৫ কোটি | J6: ২.২৫ ~ ৫ কোটি | K6: ২.২৫ ~ ৫ কোটি | L6: ৩ ~ ৫ কোটি | M6: ৩ ~ ৫ কোটি | N6: ৩ ~ ১০ কোটি | O6: ৩ ~ ১০ কোটি | P6: ৪ ~ ১০ কোটি | Q6: ৪ ~ ১০ কোটি | R6: ৪ ~ ১০ কোটি | S6: ৪ ~ ১০ কোটি | T6: ৪ ~ ১০ কোটি | U6: ৪ ~ ১০ কোটি | V6: ৪ ~ ১০ কোটি
C7: †iqvZ cieZ©x ‡gvU AvqKi | D7: ='Sheet of Calculation'!F42 -> 1463431.8 | E7: 0.2 | F7: 292686.37 | G7: ১০ ~ ২০ কোটি | I7: ৫ ~ ১০ কোটি | J7: ৫ ~ ১০ কোটি | K7: ৫ ~ ১০ কোটি | L7: ৫ ~ ১০ কোটি | M7: ৫ ~ ১০ কোটি | N7: ১০ ~ ২০ কোটি | O7: ১০ ~ ২০ কোটি | P7: ১০ ~ ২০ কোটি | Q7: ১০ ~ ২০ কোটি | R7: ১০ ~ ২০ কোটি | S7: ১০ ~ ২০ কোটি | T7: ১০ ~ ২০ কোটি | U7: ১০ ~ ২০ কোটি | V7: ১০ ~ ২০ কোটি
C8: evwo/Mvwoi mviPvR© | D8: =IF(D5=F13,(D7*E6*E13),IF(D5=F14,(D7*E5*E14),0)) -> 0 | E8: 0.3 | F8: 439029.55 | G8: ২০ ~ ৫০ কোটি | I8: ১০ ~ ১৫ কোটি | J8: ১০ ~ ১৫ কোটি | K8: ১০ ~ ১৫ কোটি | L8: ১০ ~ ১৫ কোটি | M8: ১০ ~ ১৫ কোটি | N8: ২০ ~ ৫০ কোটি | O8: ২০ ~ ৫০ কোটি | P8: ২০ ~ ৫০ কোটি | Q8: ২০ ~ ৫০ কোটি | R8: ২০ ~ ৫০ কোটি | S8: ২০ ~ ৫০ কোটি | T8: ২০ ~ ৫০ কোটি | U8: ২০ ~ ৫০ কোটি | V8: ২০ ~ ৫০ কোটি
C9: bxU m¤cwËi mviPvR© | D9: =_xlfn.XLOOKUP(D6,G5:G10,F5:F10,0) -> 0 | E9: 0.35 | F9: 512201.14 | G9: > ৫০ কোটি | I9: ১৫ ~ ২০ কোটি | J9: ১৫ ~ ২০ কোটি | K9: ১৫ ~ ২০ কোটি | L9: ১৫ ~ ২০ কোটি | M9: ১৫ ~ ২০ কোটি | N9: > ৫০ কোটি | O9: > ৫০ কোটি | P9: > ৫০ কোটি | Q9: > ৫০ কোটি | R9: > ৫০ কোটি | S9: > ৫০ কোটি | T9: > ৫০ কোটি | U9: > ৫০ কোটি | V9: > ৫০ কোটি
C10: mviPvR© | D10: =MAX(D8:D9) -> 0 | E10: 0 | F10: 0 | G10: 0 | I10: > ২০ কোটি | J10: > ২০ কোটি | K10: > ২০ কোটি | L10: > ২০ কোটি | M10: > ২০ কোটি | N10: 0 | O10: 0 | P10: 0 | Q10: 0 | R10: 0 | S10: 0 | T10: 0 | U10: 0 | V10: 0
C11: =C13 -> cwi‡ek mviPvR© | D11: =_xlfn.XLOOKUP(G4,I4:V4,I33:V33,0,1) -> 0 | F11: ="(cwi‡ek) = "&D11&"/- UvKv" -> (cwi‡ek) = 0/- UvKv | G11: .
I12: 0 | J12: 0 | K12: 0 | L12: 0 | M12: 0 | N12: 0 | O12: 0 | P12: 0 | Q12: 0 | R12: 0 | S12: 0 | T12: 0 | U12: 0 | V12: 0
C13: =_xlfn.XLOOKUP(G4,I4:V4,I32:V32,0,1) -> cwi‡ek mviPvR© | D13: 8000 et dzt evwo/GKvwaK Mvwo | E13: {=_xlfn.XLOOKUP(G4,I4:V4,I29:V30,0,1)} -> 1 | F13: {=_xlfn.XLOOKUP(G4,I4:V4,I27:V28,0,1)} -> প্রযোজ্য | I13: 0.1 | J13: 0.1 | K13: 0.1 | L13: 0.1 | M13: 0.1 | N13: 0.1 | O13: 0.1 | P13: 0.1 | Q13: 0.1 | R13: 0.1 | S13: 0.1 | T13: 0.1 | U13: 0.1 | V13: 0.1
C14: ='Data Input'!F10 -> 0 | D14: - | E14: 0 | F14: প্রযোজ্য নহে | I14: 0.15 | J14: 0.15 | K14: 0.15 | L14: 0.15 | M14: 0.15 | N14: 0.2 | O14: 0.2 | P14: 0.2 | Q14: 0.2 | R14: 0.2 | S14: 0.2 | T14: 0.2 | U14: 0.2 | V14: 0.2
C15: =IF(D11>0,F11,G11) -> . | I15: 0.2 | J15: 0.2 | K15: 0.2 | L15: 0.2 | M15: 0.2 | N15: 0.3 | O15: 0.3 | P15: 0.3 | Q15: 0.3 | R15: 0.3 | S15: 0.3 | T15: 0.3 | U15: 0.3 | V15: 0.3
I16: 0.25 | J16: 0.25 | K16: 0.25 | L16: 0.25 | M16: 0.25 | N16: 0.35 | O16: 0.35 | P16: 0.35 | Q16: 0.35 | R16: 0.35 | S16: 0.35 | T16: 0.35 | U16: 0.35 | V16: 0.35
I17: 0.3 | J17: 0.3 | K17: 0.3 | L17: 0.3 | M17: 0.3 | N17: 0 | O17: 0 | P17: 0 | Q17: 0 | R17: 0 | S17: 0 | T17: 0 | U17: 0 | V17: 0
I18: Min Surcharge /-
I19: =$D$7*I12 -> 0 | J19: =$D$7*J12 -> 0 | K19: =$D$7*K12 -> 0 | L19: =$D$7*L12 -> 0 | M19: =$D$7*M12 -> 0 | N19: =$D$7*N12 -> 0 | O19: =$D$7*O12 -> 0 | P19: =$D$7*P12 -> 0 | ... V19: =$D$7*V12 -> 0
I20: =$D$7*I13 -> 146343.18 | J20: =$D$7*J13 -> 146343.18 | K20: =IF(($D$7*K13)<=3000,3000,($D$7*K13)) -> 146343.18 | L20: =IF(($D$7*L13)<=3000,3000,($D$7*L13)) -> 146343.18 | M20: =IF(($D$7*M13)<=3000,3000,($D$7*M13)) -> 146343.18 | N20: =$D$7*N13 -> 146343.18 | O20: =$D$7*O13 -> 146343.18 | P20: =$D$7*P13 -> 146343.18 | Q20: =$D$7*Q13 -> 146343.18 | R20: =$D$7*R13 -> 146343.18 | S20: =$D$7*S13 -> 146343.18 | T20: =$D$7*T13 -> 146343.18 | U20: =$D$7*U13 -> 146343.18 | V20: =$D$7*V13 -> 146343.18
I21: =$D$7*I14 -> 219514.78 | J21: =$D$7*J14 -> 219514.78 | K21: =IF(($D$7*K14)<=3000,3000,($D$7*K14)) -> 219514.78 | L21: =IF(($D$7*L14)<=3000,3000,($D$7*L14)) -> 219514.78 | M21: =IF(($D$7*M14)<=3000,3000,($D$7*M14)) -> 219514.78 | N21: =$D$7*N14 -> 292686.37 | O21: =$D$7*O14 -> 292686.37 | P21: =$D$7*P14 -> 292686.37 | Q21: =$D$7*Q14 -> 292686.37 | R21: =$D$7*R14 -> 292686.37 | S21: =$D$7*S14 -> 292686.37 | T21: =$D$7*T14 -> 292686.37 | U21: =$D$7*U14 -> 292686.37 | V21: =$D$7*V14 -> 292686.37
I22: =$D$7*I15 -> 292686.37 | J22: =$D$7*J15 -> 292686.37 | K22: =IF(($D$7*K15)<=5000,5000,($D$7*K15)) -> 292686.37 | L22: =IF(($D$7*L15)<=5000,5000,($D$7*L15)) -> 292686.37 | M22: =IF(($D$7*M15)<=5000,5000,($D$7*M15)) -> 292686.37 | N22: =$D$7*N15 -> 439029.55 | O22: =$D$7*O15 -> 439029.55 | P22: =$D$7*P15 -> 439029.55 | Q22: =$D$7*Q15 -> 439029.55 | R22: =$D$7*R15 -> 439029.55 | S22: =$D$7*S15 -> 439029.55 | T22: =$D$7*T15 -> 439029.55 | U22: =$D$7*U15 -> 439029.55 | V22: =$D$7*V15 -> 439029.55
I23: =$D$7*I16 -> 365857.96 | J23: =$D$7*J16 -> 365857.96 | K23: =IF(($D$7*K16)<=5000,5000,($D$7*K16)) -> 365857.96 | L23: =IF(($D$7*L16)<=5000,5000,($D$7*L16)) -> 365857.96 | M23: =IF(($D$7*M16)<=5000,5000,($D$7*M16)) -> 365857.96 | N23: =$D$7*N16 -> 512201.14 | O23: =$D$7*O16 -> 512201.14 | P23: =$D$7*P16 -> 512201.14 | Q23: =$D$7*Q16 -> 512201.14 | R23: =$D$7*R16 -> 512201.14 | S23: =$D$7*S16 -> 512201.14 | T23: =$D$7*T16 -> 512201.14 | U23: =$D$7*U16 -> 512201.14 | V23: =$D$7*V16 -> 512201.14
I24: =$D$7*I17 -> 439029.55 | J24: =$D$7*J17 -> 439029.55 | K24: =IF(($D$7*K17)<=5000,5000,($D$7*K17)) -> 439029.55 | L24: =IF(($D$7*L17)<=5000,5000,($D$7*L17)) -> 439029.55 | M24: =IF(($D$7*M17)<=5000,5000,($D$7*M17)) -> 439029.55 | N24: =$D$7*N17 -> 0 | O24: =$D$7*O17 -> 0 | P24: =$D$7*P17 -> 0 | Q24: =$D$7*Q17 -> 0 | R24: =$D$7*R17 -> 0 | S24: =$D$7*S17 -> 0 | T24: =$D$7*T17 -> 0 | U24: =$D$7*U17 -> 0 | V24: =$D$7*V17 -> 0
I27: -- | J27: -- | K27: প্রযোজ্য | L27: প্রযোজ্য | M27: প্রযোজ্য | N27: প্রযোজ্য | O27: প্রযোজ্য | P27: প্রযোজ্য | Q27: প্রযোজ্য | R27: প্রযোজ্য | S27: প্রযোজ্য | T27: প্রযোজ্য | U27: প্রযোজ্য | V27: প্রযোজ্য
I28: -- | J28: -- | K28: প্রযোজ্য নহে | L28: প্রযোজ্য নহে | M28: প্রযোজ্য নহে | N28: প্রযোজ্য নহে | O28: প্রযোজ্য নহে | P28: প্রযোজ্য নহে | Q28: প্রযোজ্য নহে | R28: প্রযোজ্য নহে | S28: প্রযোজ্য নহে | T28: প্রযোজ্য নহে | U28: প্রযোজ্য নহে | V28: প্রযোজ্য নহে
I29: 0 | J29: 0 | K29: 1 | L29: 1 | M29: 1 | N29: 1 | O29: 1 | P29: 1 | Q29: 1 | R29: 1 | S29: 1 | T29: 1 | U29: 1 | V29: 1
I30: 0 | J30: 0 | K30: 0 | L30: 0 | M30: 0 | N30: 0 | O30: 0 | P30: 0 | Q30: 0 | R30: 0 | S30: 0 | T30: 0 | U30: 0 | V30: 0
I32: cwi‡ek mviPvR© (AcÖ‡hvR¨) | J32: cwi‡ek mviPvR© (AcÖ‡hvR¨) | K32: cwi‡ek mviPvR© (AcÖ‡hvR¨) | L32: cwi‡ek mviPvR© (AcÖ‡hvR¨) | M32: cwi‡ek mviPvR© (AcÖ‡hvR¨) | N32: cwi‡ek mviPvR© (AcÖ‡hvR¨) | O32: cwi‡ek mviPvR© (AcÖ‡hvR¨) | P32: cwi‡ek mviPvR© | Q32: cwi‡ek mviPvR© | R32: cwi‡ek mviPvR© | S32: cwi‡ek mviPvR© | T32: cwi‡ek mviPvR© | U32: cwi‡ek mviPvR© | V32: cwi‡ek mviPvR©
I33: =$C$14*0 -> 0 | J33: =$C$14*0 -> 0 | K33: =$C$14*0 -> 0 | L33: =$C$14*0 -> 0 | M33: =$C$14*0 -> 0 | N33: =$C$14*0 -> 0 | O33: =$C$14*0 -> 0 | P33: =$C$14*1 -> 0 | Q33: =$C$14*1 -> 0 | R33: =$C$14*1 -> 0 | S33: =$C$14*1 -> 0 | T33: =$C$14*1 -> 0 | U33: =$C$14*1 -> 0 | V33: =$C$14*1 -> 0
I58: Aby‡gvw`Z wewb‡qvM | J58: Aby‡gvw`Z wewb‡qvM | K58: Aby‡gvw`Z wewb‡qvM | L58: Aby‡gvw`Z wewb‡qvM | M58: Aby‡gvw`Z wewb‡qvM | N58: Aby‡gvw`Z wewb‡qvM | O58: Aby‡gvw`Z wewb‡qvM | P58: Aby‡gvw`Z wewb‡qvM I e¨q | Q58: Aby‡gvw`Z wewb‡qvM I e¨q | R58: Aby‡gvw`Z wewb‡qvM I e¨q | S58: Aby‡gvw`Z wewb‡qvM I e¨q | T58: Aby‡gvw`Z wewb‡qvM I e¨q | U58: Aby‡gvw`Z wewb‡qvM I e¨q | V58: Aby‡gvw`Z wewb‡qvM I e¨q
I59: †iqvZ‡hvM¨ wewb‡qvM | J59: †iqvZ‡hvM¨ wewb‡qvM | K59: †iqvZ‡hvM¨ wewb‡qvM | L59: †iqvZ‡hvM¨ wewb‡qvM | M59: †iqvZ‡hvM¨ wewb‡qvM | N59: †iqvZ‡hvM¨ wewb‡qvM | O59: †iqvZ‡hvM¨ wewb‡qvM | P59: †iqvZ‡hvM¨ wewb‡qvM I e¨q | Q59: †iqvZ‡hvM¨ wewb‡qvM I e¨q | R59: †iqvZ‡hvM¨ wewb‡qvM I e¨q | S59: †iqvZ‡hvM¨ wewb‡qvM I e¨q | T59: †iqvZ‡hvM¨ wewb‡qvM I e¨q | U59: †iqvZ‡hvM¨ wewb‡qvM I e¨q | V59: †iqvZ‡hvM¨ wewb‡qvM I e¨q
C60: Ki †iqvZ cwiMYbv | I60: {=TRANSPOSE('MisC Intrst-3'!R10:R23)} -> 2016-17 | J60: 2017-18 | K60: 2018-19 | L60: 2019-20 | M60: 2020-21 | N60: 2021-22 | O60: 2022-23 | P60: 2023-24 | Q60: 2024-25 | R60: 2025-26 | S60: 2026-27 | T60: 2027-28 | U60: 2028-29 | V60: 2029-30
C61: wbqwgZ ‡gvU Avq (163 Avq e¨wZZ) | D61: {=_xlfn.XLOOKUP(G4,_xlfn.ANCHORARRAY(I60),I63:V63,0,1)} -> 12152852 | F61: Elligible Investment: Total Income x(20% or 25% or 3%) | G61: {=_xlfn.XLOOKUP(G4,_xlfn.ANCHORARRAY(I60),I61:V61,0,1)} -> 0.03 | I61: 0.25 | J61: 0.25 | K61: 0.25 | L61: 0.25 | M61: 0.25 | N61: 0.25 | O61: 0.2 | P61: 0.03 | Q61: 0.03 | R61: 0.03 | S61: 0.03 | T61: 0.03 | U61: 0.03 | V61: 0.03
C62: {="wbqwgZ ‡gvU Av‡qi "&_xlfn.XLOOKUP(G4,_xlfn.ANCHORARRAY(I60),I62:V62,0,1)&"%"} -> wbqwgZ ‡gvU Av‡qi 3% | D62: =D61*G61 -> 364585.56 | F62: wbqwgZ ‡gvU Avq (163 Avq e¨wZZ) | G62: ='Data Input'!E33 -> 5462355 | I62: 25 | J62: 25 | K62: 25 | L62: 25 | M62: 25 | N62: 25 | O62: 20 | P62: 3 | Q62: 3 | R62: 3 | S62: 3 | T62: 3 | U62: 3 | V62: 3
C63: {="ev, "&_xlfn.XLOOKUP(G4,_xlfn.ANCHORARRAY(I60),I65:V65,0,1)} -> ev, †iqvZ‡hvM¨ (wewb‡qvM I e¨‡qi) 15% | D63: {=_xlfn.XLOOKUP(G4,_xlfn.ANCHORARRAY(I60),I64:V64,0,1)} -> 148535.25 | F63: {=_xlfn.XLOOKUP(G4,_xlfn.ANCHORARRAY(I60),I59:V59,0,1)} -> †iqvZ‡hvM¨ wewb‡qvM I e¨q | G63: ='Data Input'!E39 -> 990235 | I63: =$G$62 -> 5462355 | J63: =$G$62 -> 5462355 | K63: =$G$62 -> 5462355 | L63: =$G$62 -> 5462355 | M63: =$G$62 -> 5462355 | N63: =$G$62 -> 5462355 | O63: =$G$62 -> 5462355 | P63: =$G$62 -> 5462355 | Q63: =$G$62 -> 5462355 | R63: =$G$64 -> 12152852 | S63: =$G$64 -> 12152852 | T63: =$G$64 -> 12152852 | U63: =$G$64 -> 12152852 | V63: =$G$64 -> 12152852
C64: {="ev, "&_xlfn.XLOOKUP(G4,_xlfn.ANCHORARRAY(I60),I66:V66,0,1)&" UvKv"} -> ev, 10 j¶ UvKv | D64: {=_xlfn.XLOOKUP(G4,_xlfn.ANCHORARRAY(I60),I67:V67,0,1)} -> 1000000 | F64: wbqwgZ Avq + 163 Avq - dv‡g©i Kiv‡ivwcZ Avq | G64: ='Data Input'!E33+'Data Input'!E36-'Data Input'!E31 -> 12152852 | I64: =$G$63 -> 990235 | J64: =$G$63 -> 990235 | K64: =$G$63 -> 990235 | L64: =$G$63 -> 990235 | M64: =$G$63 -> 990235 | N64: =$G$63 -> 990235 | O64: =$G$63 -> 990235 | P64: =$G$63*0.15 -> 148535.25 | Q64: =$G$63*0.15 -> 148535.25 | R64: =$G$63*0.15 -> 148535.25 | S64: =$G$63*0.15 -> 148535.25 | T64: =$G$63*0.15 -> 148535.25 | U64: =$G$63*0.15 -> 148535.25 | V64: =$G$63*0.15 -> 148535.25
C65: me‡P‡q †QvU | D65: =MIN(D62:D64) -> 148535.25 | F65: ='MisC Cal-1'!B133 -> ব্যক্তিসংঘ/ফার্মের করারোপিত শেয়ার আয় | G65: ='Data Input'!E31 -> 500000 | I65: =I59 -> †iqvZ‡hvM¨ wewb‡qvM | J65: =J59 -> †iqvZ‡hvM¨ wewb‡qvM | K65: =K59 -> †iqvZ‡hvM¨ wewb‡qvM | L65: =L59 -> †iqvZ‡hvM¨ wewb‡qvM | M65: =M59 -> †iqvZ‡hvM¨ wewb‡qvM | N65: =N59 -> †iqvZ‡hvM¨ wewb‡qvM | O65: =O59 -> †iqvZ‡hvM¨ wewb‡qvM | P65: †iqvZ‡hvM¨ (wewb‡qvM I e¨‡qi) 15% | Q65: †iqvZ‡hvM¨ (wewb‡qvM I e¨‡qi) 15% | R65: †iqvZ‡hvM¨ (wewb‡qvM I e¨‡qi) 15% | S65: †iqvZ‡hvM¨ (wewb‡qvM I e¨‡qi) 15% | T65: †iqvZ‡hvM¨ (wewb‡qvM I e¨‡qi) 15% | U65: †iqvZ‡hvM¨ (wewb‡qvM I e¨‡qi) 15% | V65: †iqvZ‡hvM¨ (wewb‡qvM I e¨‡qi) 15%
C66: {=_xlfn.XLOOKUP(G4,_xlfn.ANCHORARRAY(I60),I58:V58,0,1)&" = "&D65&"/-"} -> Aby‡gvw`Z wewb‡qvM I e¨q = 148535.25/- | D66: =D65 -> 148535.25 | F66: wbqwgZ Drm n‡Z ‡gvU Avq | G66: ='Data Input'!E33 -> 5462355 | I66: 1.50 †KvwU | J66: 1.50 †KvwU | K66: 1.50 †KvwU | L66: 1.50 †KvwU | M66: 1.50 †KvwU | N66: 1.00 †KvwU | O66: 1.00 †KvwU | P66: 10 j¶ | Q66: 10 j¶ | R66: 10 j¶ | S66: 10 j¶ | T66: 10 j¶ | U66: 10 j¶ | V66: 10 j¶
C67: wbqwgZ ‡gvU Av‡qi Rb¨ †iqvZ | D67: {=_xlfn.XLOOKUP(G4,_xlfn.ANCHORARRAY(I60),I68:V68,0,1)} -> 148535.25 | F67: cÖK…Z AvqKi (wbqwgZ Dr‡mi Avq n‡Z) | G67: ='MisC Cal-1'!L6 -> 1203706.5 | I67: 15000000 | J67: 15000000 | K67: 15000000 | L67: 15000000 | M67: 15000000 | N67: 10000000 | O67: 10000000 | P67: 1000000 | Q67: 1000000 | R67: 1000000 | S67: 1000000 | T67: 1000000 | U67: 1000000 | V67: 1000000
C68: e¨w³msN/dv‡g©i Av‡qi Rb¨ Ki Ae¨vnwZ | D68: =IF(G68>=0,G68,0) -> 110182.01 | F68: Kiv‡ivwcZ Av‡qi Mo nv‡i Ki`vq (80 avivq) | G68: =G67*(G65/G66) -> 110182.01 | H68: Rebate | I68: =$H$89 -> 22280.287 | J68: =$H$89 -> 22280.287 | K68: =$H$89 -> 22280.287 | L68: =$H$98 -> 14853.525 | M68: =$H$98 -> 14853.525 | N68: =$H$98 -> 14853.525 | O68: =H103 -> 22280.287 | P68: =$D$65 -> 148535.25 | Q68: =$D$65 -> 148535.25 | R68: =$D$65 -> 148535.25 | S68: =$D$65 -> 148535.25 | T68: =$D$65 -> 148535.25 | U68: =$D$65 -> 148535.25 | V68: =$D$65 -> 148535.25
C69: ‡gvU †iqvZ | D69: =D68+D67 -> 258717.26
H71: Gross Salary | I71: ='MisC Cal-1'!$I$90 -> 1600000 | J71: ='MisC Cal-1'!$I$90 -> 1600000 | K71: ='MisC Cal-1'!$I$90 -> 1600000 | L71: ='MisC Cal-1'!$I$90 -> 1600000 | M71: ='MisC Cal-1'!$I$90 -> 1600000 | N71: ='MisC Cal-1'!$I$90 -> 1600000 | O71: ='MisC Cal-1'!$I$90 -> 1600000 | P71: ='MisC Cal-1'!$I$90 -> 1600000 | ... V71: ='MisC Cal-1'!$I$90 -> 1600000
C72: dv‡g©i Askx`vix Avqt | H72: Tax Exempted | I72: ='MisC Cal-1'!$J$90 -> 0 | J72: ='MisC Cal-1'!$J$90 -> 0 | K72: ='MisC Cal-1'!$J$90 -> 0 | L72: ='MisC Cal-1'!$J$90 -> 0 | M72: ='MisC Cal-1'!$J$90 -> 0 | N72: ='MisC Cal-1'!$J$90 -> 0 | O72: ='MisC Cal-1'!$J$90 -> 0 | P72: =MIN((P71/3),450000) -> 450000 | Q72: =MIN((Q71/3),450000) -> 450000 | R72: =MIN((R71/3),500000) -> 500000 | S72: =MIN((S71/3),500000) -> 500000 | T72: =MIN((T71/3),500000) -> 500000 | U72: =MIN((U71/3),500000) -> 500000 | V72: =MIN((V71/3),500000) -> 500000
C73: ="*("&C68&" = "&ROUNDUP(D68,0)&"/-)" -> *(e¨w³msN/dv‡g©i Av‡qi Rb¨ Ki Ae¨vnwZ = 110183/-) | H73: Net Salary | I73: ='MisC Cal-1'!$K$90 -> 1600000 | J73: ='MisC Cal-1'!$K$90 -> 1600000 | K73: ='MisC Cal-1'!$K$90 -> 1600000 | L73: ='MisC Cal-1'!$K$90 -> 1600000 | M73: ='MisC Cal-1'!$K$90 -> 1600000 | N73: ='MisC Cal-1'!$K$90 -> 1600000 | O73: ='MisC Cal-1'!$K$90 -> 1600000 | P73: =P71-P72 -> 1150000 | Q73: =Q71-Q72 -> 1150000 | R73: =R71-R72 -> 1100000 | S73: =S71-S72 -> 1100000 | T73: =T71-T72 -> 1100000 | U73: =U71-U72 -> 1100000 | V73: =V71-V72 -> 1100000
C74: *(†KejgvÎ wbqwgZ Ki`v‡qi mv‡_ mgš^q‡hvM¨ )
F75: Actual Tax Day | G75: ='MisC Intrst-3'!O36 -> 45991 | H75: 174 Delay Interest Charge | I75: =I71 -> 1600000 | J75: =J71 -> 1600000 | K75: =K71 -> 1600000 | L75: =L71 -> 1600000 | M75: =M71 -> 1600000 | N75: =N71 -> 1600000 | O75: =O71 -> 1600000 | P75: =P71 -> 1600000 | ... V75: =V71 -> 1600000
C76: =IF(D68>0,C73,C74) -> *(e¨w³msN/dv‡g©i Av‡qi Rb¨ Ki Ae¨vnwZ = 110183/-) | F76: Return Submission | G76: ='Data Input'!D5 -> 45962 | I76: =I72 -> 0 | J76: =J72 -> 0 | K76: =K72 -> 0 | L76: =L72 -> 0 | M76: =M72 -> 0 | N76: =N72 -> 0 | O76: =O72 -> 0 | P76: =IF($G$77>0,0,P72) -> 450000 | Q76: =IF($G$77>0,0,Q72) -> 450000 | R76: =IF($G$77>0,0,R72) -> 500000 | S76: =IF($G$77>0,0,S72) -> 500000 | T76: =IF($G$77>0,0,T72) -> 500000 | U76: =IF($G$77>0,0,U72) -> 500000 | V76: =IF($G$77>0,0,V72) -> 500000
F77: Difference | G77: =G76-G75 -> -29 | I77: =I75-I76 -> 1600000 | J77: =J75-J76 -> 1600000 | K77: =K75-K76 -> 1600000 | L77: =L75-L76 -> 1600000 | M77: =M75-M76 -> 1600000 | N77: =N75-N76 -> 1600000 | O77: =O75-O76 -> 1600000 | P77: =P75-P76 -> 1150000 | ... V77: =V75-V76 -> 1100000
F79: Return Submission | G79: ='Data Input'!D5 -> 45962 | H79: 174 Section before 2023-24 | I79: ='MisC Cal-1'!$I$90 -> 1600000 | J79: ='MisC Cal-1'!$I$90 -> 1600000 | K79: ='MisC Cal-1'!$I$90 -> 1600000 | L79: ='MisC Cal-1'!$I$90 -> 1600000 | M79: ='MisC Cal-1'!$I$90 -> 1600000 | N79: ='MisC Cal-1'!$I$90 -> 1600000 | O79: ='MisC Cal-1'!$I$90 -> 1600000 | P79: ='MisC Cal-1'!$I$90 -> 1600000 | ... V79: ='MisC Cal-1'!$I$90 -> 1600000
F80: Income Tax Act, 2023 Enacts: | G80: =DATE(2023,7,1) -> 45108 | I80: =IF($G$81>=0,0,I72) -> 0 | J80: =IF($G$81>=0,0,J72) -> 0 | K80: =IF($G$81>=0,0,K72) -> 0 | L80: =IF($G$81>=0,0,L72) -> 0 | M80: =IF($G$81>=0,0,M72) -> 0 | N80: =IF($G$81>=0,0,N72) -> 0 | O80: =IF($G$81>=0,0,O72) -> 0 | P80: =IF($G$77>0,0,P72) -> 450000 | Q80: =IF($G$77>0,0,Q72) -> 450000 | R80: =IF($G$77>0,0,R72) -> 500000 | S80: =IF($G$77>0,0,S72) -> 500000 | T80: =IF($G$77>0,0,T72) -> 500000 | U80: =IF($G$77>0,0,U72) -> 500000 | V80: =IF($G$77>0,0,V72) -> 500000
F81: Difference(174 Tax) | G81: =G79-G80 -> 854 | I81: =I79-I80 -> 1600000 | J81: =J79-J80 -> 1600000 | K81: =K79-K80 -> 1600000 | L81: =L79-L80 -> 1600000 | M81: =M79-M80 -> 1600000 | N81: =N79-N80 -> 1600000 | O81: =O79-O80 -> 1600000 | P81: =P79-P80 -> 1150000 | ... V81: =V79-V80 -> 1100000
G82: Old/New 174 | H82: {=_xlfn.XLOOKUP(G4,_xlfn.ANCHORARRAY(I60),'MisC Cal-2'!I82:V82,0,1)} -> 0 | I82: =IF($G$81>=0,"OLD 174",0) -> OLD 174 | J82: =IF($G$81>=0,"OLD 174",0) -> OLD 174 | K82: =IF($G$81>=0,"OLD 174",0) -> OLD 174 | L82: =IF($G$81>=0,"OLD 174",0) -> OLD 174 | M82: =IF($G$81>=0,"OLD 174",0) -> OLD 174 | N82: =IF($G$81>=0,"OLD 174",0) -> OLD 174 | O82: =IF($G$81>=0,"OLD 174",0) -> OLD 174 | P82: =IF($G$77>=0,"New 174",0) -> 0 | Q82: =IF($G$77>=0,"New 174",0) -> 0 | R82: =IF($G$77>=0,"New 174",0) -> 0 | S82: =IF($G$77>=0,"New 174",0) -> 0 | T82: =IF($G$77>=0,"New 174",0) -> 0 | U82: =IF($G$77>=0,"New 174",0) -> 0 | V82: =IF($G$77>=0,"New 174",0) -> 0
C89: =D61 -> 12152852 | D89: =D65 -> 148535.25 | E89: 2016-17 | F89: 2017-18 | G89: 2018-19 | H89: =IF(D61<=C91,H91,IF(D61<=C92,H92,IF(D61>C92,H94,0))) -> 22280.287
C91: 1000000 | D91: =D65 -> 148535.25 | E91: =D91 -> 148535.25 | F91: 0.15 | G91: =MIN(D91:E91)*F91 -> 22280.287 | H91: =G91 -> 22280.287
C92: 3000000 | D92: =D65 -> 148535.25 | E92: 250000 | F92: 0.15 | G92: =MIN(D92:E92)*F92 -> 22280.287 | H92: =SUM(G92:G93) -> 22280.287
C93: Rest | D93: =IF(D92>E92,(D92-E92),0) -> 0 | E93: =D93 -> 0 | F93: 0.12 | G93: =MIN(D93:E93)*F93 -> 0
C94: 3000000 | D94: =D65 -> 148535.25 | E94: 250000 | F94: 0.15 | G94: =MIN(D94:E94)*F94 -> 22280.287 | H94: =SUM(G94:G96) -> 22280.287
D95: =IF(D94>E94,(D94-E94),0) -> 0 | E95: 500000 | F95: 0.12 | G95: =MIN(D95:E95)*F95 -> 0
C96: Rest | D96: =IF(D95>E95,(D95-E95),0) -> 0 | E96: =D96 -> 0 | F96: 0.1 | G96: =MIN(D96:E96)*F96 -> 0
C98: =D61 -> 12152852 | D98: =D65 -> 148535.25 | E98: 2019-20 | F98: 2020-21 | G98: 2021-22 | H98: =IF(D61<=C100,H100,IF(D61>C100,H101,0)) -> 14853.525
C100: 1500000 | D100: =D65 -> 148535.25 | E100: =D100 -> 148535.25 | F100: 0.15 | G100: =MIN(D100:E100)*F100 -> 22280.287 | H100: =G100 -> 22280.287
D101: =D65 -> 148535.25 | E101: =D101 -> 148535.25 | F101: 0.1 | G101: =MIN(D101:E101)*F101 -> 14853.525 | H101: =G101 -> 14853.525
C103: =D61 -> 12152852 | D103: =D65 -> 148535.25 | F103: 2022-23 | H103: =_xlfn.XLOOKUP(F108,G108:G110,H108:H110,0) -> 22280.287
C105: 1500000 | D105: =D65 -> 148535.25 | E105: =D105 -> 148535.25 | F105: 0.15 | G105: =MIN(D105:E105)*F105 -> 22280.287 | H105: =G105 -> 22280.287
C106: After Tax Day | D106: =D65 -> 148535.25 | E106: =D106 -> 148535.25 | F106: 0.075 | G106: =MIN(D106:E106)*F106 -> 11140.144 | H106: =G106 -> 11140.144
F108: ='Data Input'!D9 -> স্বনির্ধারণী | G108: ='MisC Intrst-3'!N32 -> স্বনির্ধারণী | H108: =$H$105 -> 22280.287
G109: ='MisC Intrst-3'!N33 -> নতুন করদাতা | H109: =$H$105 -> 22280.287
G110: ='MisC Intrst-3'!N34 -> সাধারণ (বিলম্ব সুদ) | H110: =H106 -> 11140.144

Sheet MisC Intrst-3
D2: Simple & Delay Interest | W2: Sample Date | X2: =DATE(2019,7,1) -> 43647
K3: Assessmet Year | L3: ='Data Input'!D4 -> 2025-26
K4: Return Submit | L4: ='Data Input'!D5 -> 45962 | M4: I.Y Ends = | N4: =_xlfn.XLOOKUP(L3,R10:R23,T10:T23,0) -> 45838 | O4: Days
K5: Assessment Date | L5: ='Data Input'!F5 -> 46386 | M5: I.Y Starts= | N5: =_xlfn.XLOOKUP(L3,R10:R23,S10:S23,0) -> 45474 | O5: Barred Time
B6: Net Tax | C6: ='Sheet of Calculation'!F44 -> 1463431.8 | G6: 75% of Tax | H6: =C6*0.75 -> 1097573.9 | K6: Actual Tax Day | L6: =O36 -> 45991 | M6: A.Y. Starts= | N6: =_xlfn.XLOOKUP(L3,R10:R23,U10:U23,0) -> 45839 | O6: =(N7-N6) -> 730 | R6: 10 | S6: 15 | T6: 160 or 162 Int.(prev. 70 or 73 u/s)
B7: Source . tax | C7: ='Data Input'!F33+'Data Input'!F35+'Data Input'!F37+'Data Input'!E44+'Data Input'!E45 -> 739000 | G7: =B7 -> Source . tax | H7: =C7 -> 739000 | M7: Time Barred | N7: =_xlfn.XLOOKUP(L3,R10:R23,AM10:AM23,0) -> 46569 | R7: =IF(R41="OLD 174",4,2)% -> 0.02 | S7: =_xlfn.XLOOKUP(L3,R10:R23,AN10:AN23,0)% -> 0.02 | T7: Dealy Int. Rate 174 u.s (prev.73A section) | Y7: =MIN(IF((($L$35-$L$34)/30)<0,0,(($L$35-$L$34)/30)),12) -> 0 | AK7: =IF($N$30=$N$34,$L$42,0) -> 0
B8: 173 Tax | C8: ='Data Input'!E46 -> 0 | G8: Rest | H8: =H6-H7 -> 358573.88 | I8: D1 | M8: A.Y Ends | N8: =_xlfn.XLOOKUP(L3,R10:R23,V10:V23,0) -> 46203 | Y8: =ROUNDUP(MIN(IF((($L$35-$L$34)/30)<0,0,(($L$35-$L$34)/30)),24),0) -> 0 | Z8: 1st Slab | AA8: 2nd Slab | AK8: =$L$42 -> 0
G9: Rest-173 Tax | H9: =H8-C8 -> 358573.88 | I9: D2 | K9: Rate | L9: =IF((L4-L6)>0,S6,R6) -> 10 | M9: % | R9: Assessment Years | S9: I.Y Starts | T9: I.Y Ends | U9: A.Y Starts | V9: A.Y Ends | W9: Assumed Tax Day | X9: Delay Rate | Y9: Interval Months | Z9: ='Data Input'!D8 -> পুরুষ | AA9: Slab | AB9: 2nd Rate | AC9: 3rd Slab | AD9: 4th Slab | AE9: 5th Slab | AF9: Tax Date | AG9: Actual Tax Day | AH9: Tax Date (new) | AI9: New Tax Payee | AJ9: Delay Interst Difference | AK9: Dealy Intrst (82BB/Normal) | AL9: Salary Input Year Based | AM9: Time Barred | AN9: ITA, 2023 174 Rate % | AO9: Tax Paid (AIT+TDS), u/s 174 | AP9: 6th/ Final Slab | AQ9: Final Slab Calculation | AR9: 163 Calculation, final Slab
B10: Upto Return Submission, t1 | D10: =IF((L4-N6)<0,0,((L4-N6)+1)) -> 124 | R10: 2016-17 | S10: =DATE(2015,7,1) -> 42186 | T10: =S10+365 -> 42551 | U10: =T10+1 -> 42552 | V10: =U10+364 -> 42916 | W10: =U10+152 -> 42704 | X10: =$R$7 -> 0.02 | Y10: =IF($R$41="OLD 174",$Y$8,$Y$7) -> 0 | Z10: {=TRANSPOSE(_xlfn.ANCHORARRAY('MisC Cal-1'!C54))} -> 250000 | AA10: 400000 | AB10: 0.1 | AC10: 500000 | AD10: 600000 | AE10: 3000000 | AF10: ৩০ নভেম্বর | AG10: =W10 -> 42704 | AH10: ৩০ নভেম্বর | AI10: =AG10 -> 42704 | AJ10: =IF($R$41="OLD 174",$M$34,$L$33) -> 724431.84 | AK10: =IF($R$41="OLD 174",$AK$8,$AK$7) -> 0 | AL10: Yes | AM10: =U10+(365*2) -> 43282 | AN10: 4 | AO10: 0 | AP10: Aewkó | AQ10: =('Sheet of Calculation'!$C$35)*('Sheet of Calculation'!$E$35) -> 903088.75 | AR10: =('MisC Cal-1'!$C$15)*('MisC Cal-1'!$E$15) -> 1335124.2
B11: Logical, t1 | D11: =IF(D10>G12,G12,D10) -> 124 | R11: 2017-18 | S11: =U10 -> 42552 | T11: =S11+364 -> 42916 | U11: =T11+1 -> 42917 | V11: =U11+364 -> 43281 | W11: =U11+152 -> 43069 | X11: =$R$7 -> 0.02 | Y11: =IF($R$41="OLD 174",$Y$8,$Y$7) -> 0 | Z11: 250000 | AA11: 400000 | AB11: 0.1 | AC11: 500000 | AD11: 600000 | AE11: 3000000 | AF11: ৩০ নভেম্বর | AG11: =W11 -> 43069 | AH11: ৩০ নভেম্বর | AI11: =AG11 -> 43069 | AJ11: =IF($R$41="OLD 174",$M$34,$L$33) -> 724431.84 | AK11: =IF($R$41="OLD 174",$AK$8,$AK$7) -> 0 | AL11: Yes | AM11: =U11+(365*2) -> 43647 | AN11: 4 | AO11: 0 | AP11: Aewkó | AQ11: =('Sheet of Calculation'!$C$35)*('Sheet of Calculation'!$E$35) -> 903088.75 | AR11: =('MisC Cal-1'!$C$15)*('MisC Cal-1'!$E$15) -> 1335124.2
B12: 74 to Assessment Date, t2 | D12: =IF((L5-L4)<0,0,(L5-L4)) -> 424 | F12: Barred Time | G12: =O6 -> 730 | I12: D1 | J12: =IF(H8>0,H8,0) -> 358573.88 | R12: 2018-19 | S12: =U11 -> 42917 | T12: =S12+364 -> 43281 | U12: =T12+1 -> 43282 | V12: =U12+364 -> 43646 | W12: =U12+152 -> 43434 | X12: =$R$7 -> 0.02 | Y12: =IF($R$41="OLD 174",$Y$8,$Y$7) -> 0 | Z12: 250000 | AA12: 400000 | AB12: 0.1 | AC12: 500000 | AD12: 600000 | AE12: 3000000 | AF12: ৩০ নভেম্বর | AG12: =W12 -> 43434 | AH12: ৩০ নভেম্বর | AI12: =AG12 -> 43434 | AJ12: =IF($R$41="OLD 174",$M$34,$L$33) -> 724431.84 | AK12: =IF($R$41="OLD 174",$AK$8,$AK$7) -> 0 | AL12: Yes | AM12: =U12+(365*2)+1 -> 44013 | AN12: 4 | AO12: 0 | AP12: Aewkó | AQ12: =('Sheet of Calculation'!$C$35)*('Sheet of Calculation'!$E$35) -> 903088.75 | AR12: =('MisC Cal-1'!$C$15)*('MisC Cal-1'!$E$15) -> 1335124.2
B13: Total | D13: =SUM(D11:D12) -> 548 | F13: 730 - t1 | G13: =IF(G12>D11,G12-D11,0) -> 606 | I13: D2 | J13: =IF(H9>0,H9,0) -> 358573.88 | R13: 2019-20 | S13: =U12 -> 43282 | T13: =S13+364 -> 43646 | U13: =T13+1 -> 43647 | V13: =U13+365 -> 44012 | W13: =U13+152 -> 43799 | X13: =$R$7 -> 0.02 | Y13: =IF($R$41="OLD 174",$Y$8,$Y$7) -> 0 | Z13: 250000 | AA13: 400000 | AB13: 0.1 | AC13: 500000 | AD13: 600000 | AE13: 3000000 | AF13: ৩০ নভেম্বর | AG13: =W13 -> 43799 | AH13: ৩০ নভেম্বর | AI13: =AG13 -> 43799 | AJ13: =IF($R$41="OLD 174",$M$34,$L$33) -> 724431.84 | AK13: =IF($R$41="OLD 174",$AK$8,$AK$7) -> 0 | AL13: Yes | AM13: =U13+(365*2)+1 -> 44378 | AN13: 4 | AO13: 0 | AP13: Aewkó | AQ13: =('Sheet of Calculation'!$C$35)*('Sheet of Calculation'!$E$35) -> 903088.75 | AR13: =('MisC Cal-1'!$C$15)*('MisC Cal-1'!$E$15) -> 1335124.2
B14: P1 | C14: D1 x T1 | D14: =((J12*J14)*L9%)/365 -> 12181.688 | F14: Actual T2 | G14: =IF(D13>G12,G13,D12) -> 424 | I14: T1 | J14: =D11 -> 124 | R14: 2020-21 | S14: =U13 -> 43647 | T14: =S14+365 -> 44012 | U14: =T14+1 -> 44013 | V14: =U14+364 -> 44377 | W14: =U14+152 -> 44165 | X14: =$R$7 -> 0.02 | Y14: =IF($R$41="OLD 174",$Y$8,$Y$7) -> 0 | Z14: 300000 | AA14: 100000 | AB14: 0.05 | AC14: 300000 | AD14: 400000 | AE14: 500000 | AF14: ৩১ ডিসেম্বর | AG14: =W14+31 -> 44196 | AH14: ৩১ ডিসেম্বর | AI14: =AG14 -> 44196 | AJ14: =IF($R$41="OLD 174",$M$34,$L$33) -> 724431.84 | AK14: =IF($R$41="OLD 174",$AK$8,$AK$7) -> 0 | AL14: Yes | AM14: =U14+(365*2) -> 44743 | AN14: 4 | AO14: 0 | AP14: Aewkó | AQ14: =('Sheet of Calculation'!$C$35)*('Sheet of Calculation'!$E$35) -> 903088.75 | AR14: =('MisC Cal-1'!$C$15)*('MisC Cal-1'!$E$15) -> 1335124.2
B15: P2 | C15: D2 xT2 | D15: =((J13*J15)*L9%)/365 -> 41653.514 | I15: T2 | J15: =G14 -> 424 | R15: 2021-22 | S15: =U14 -> 44013 | T15: =S15+364 -> 44377 | U15: =T15+1 -> 44378 | V15: =U15+364 -> 44742 | W15: =U15+152 -> 44530 | X15: =$R$7 -> 0.02 | Y15: =IF($R$41="OLD 174",$Y$8,$Y$7) -> 0 | Z15: 300000 | AA15: 100000 | AB15: 0.05 | AC15: 300000 | AD15: 400000 | AE15: 500000 | AF15: ৩১ ডিসেম্বর | AG15: =W15+31 -> 44561 | AH15: ৩১ ডিসেম্বর | AI15: =AG15 -> 44561 | AJ15: =IF($R$41="OLD 174",$M$34,$L$33) -> 724431.84 | AK15: =IF($R$41="OLD 174",$AK$8,$AK$7) -> 0 | AL15: Yes | AM15: =U15+(365*2) -> 45108 | AN15: 4 | AO15: 0 | AP15: Aewkó | AQ15: =('Sheet of Calculation'!$C$35)*('Sheet of Calculation'!$E$35) -> 903088.75 | AR15: =('MisC Cal-1'!$C$15)*('MisC Cal-1'!$E$15) -> 1335124.2
B16: Interest | C16: I = | D16: =SUM(D14:D15) -> 53835.202 | R16: 2022-23 | S16: =U15 -> 44378 | T16: =S16+364 -> 44742 | U16: =T16+1 -> 44743 | V16: =U16+364 -> 45107 | W16: =U16+152 -> 44895 | X16: =$R$7 -> 0.02 | Y16: =IF($R$41="OLD 174",$Y$8,$Y$7) -> 0 | Z16: 300000 | AA16: 100000 | AB16: 0.05 | AC16: 300000 | AD16: 400000 | AE16: 500000 | AF16: ০১ জানুয়ারী | AG16: =W16+32 -> 44927 | AH16: ৩০ জুন | AI16: =AG16+180 -> 45107 | AJ16: =IF($R$41="OLD 174",$M$34,$L$33) -> 724431.84 | AK16: =IF($R$41="OLD 174",$AK$8,$AK$7) -> 0 | AL16: Yes | AM16: =U16+(365*2)+1 -> 45474 | AN16: 4 | AO16: 0 | AP16: Aewkó | AQ16: =('Sheet of Calculation'!$C$35)*('Sheet of Calculation'!$E$35) -> 903088.75 | AR16: =('MisC Cal-1'!$C$15)*('MisC Cal-1'!$E$15) -> 1335124.2
B17: Real Interest | C17: =IF((L4-N6)<0,0,D16) -> 53835.202 | D17: =IF((L5-L4)<0,0,C17) -> 53835.202 | R17: 2023-24 | S17: =U16 -> 44743 | T17: =S17+364 -> 45107 | U17: =T17+1 -> 45108 | V17: =U17+365 -> 45473 | W17: =U17+152 -> 45260 | X17: =$S$7 -> 0.02 | Y17: =$Y$8 -> 0 | Z17: 350000 | AA17: 100000 | AB17: 0.05 | AC17: 300000 | AD17: 400000 | AE17: 500000 | AF17: ৩০ নভেম্বর | AG17: =W17+62 -> 45322 | AH17: ৩০ জুন | AI17: =AG17+151 -> 45473 | AJ17: =$M$34 -> 724431.84 | AK17: =$L$42 -> 0 | AL17: No | AM17: =U17+(365*2)+1 -> 45839 | AN17: 4 | AO17: 0 | AP17: Aewkó | AQ17: =('Sheet of Calculation'!$C$35)*('Sheet of Calculation'!$E$35) -> 903088.75 | AR17: =('MisC Cal-1'!$C$15)*('MisC Cal-1'!$E$15) -> 1335124.2
B18: Real Interest | C18: I = | D18: =D17 -> 53835.202 | R18: 2024-25 | S18: =U17 -> 45108 | T18: =S18+365 -> 45473 | U18: =T18+1 -> 45474 | V18: =U18+364 -> 45838 | W18: =U18+152+31 -> 45657 | X18: =$S$7 -> 0.02 | Y18: =$Y$8 -> 0 | Z18: 350000 | AA18: 100000 | AB18: 0.05 | AC18: 400000 | AD18: 500000 | AE18: 500000 | AF18: ৩০ নভেম্বর | AG18: =W18 -> 45657 | AH18: ৩০ জুন | AI18: =AG18+212 -> 45869 | AJ18: =$M$34 -> 724431.84 | AK18: =$L$42 -> 0 | AL18: No | AM18: =U18+(365*2) -> 46204 | AN18: 2 | AO18: =$L$32 -> 739000 | AP18: Aewkó | AQ18: =('Sheet of Calculation'!$C$35)*('Sheet of Calculation'!$E$35) -> 903088.75 | AR18: =('MisC Cal-1'!$C$15)*('MisC Cal-1'!$E$15) -> 1335124.2
R19: 2025-26 | S19: =U18 -> 45474 | T19: =S19+364 -> 45838 | U19: =T19+1 -> 45839 | V19: =U19+364 -> 46203 | W19: =U19+152 -> 45991 | X19: =$S$7 -> 0.02 | Y19: =$Y$8 -> 0 | Z19: 350000 | AA19: 100000 | AB19: 0.05 | AC19: 400000 | AD19: 500000 | AE19: 500000 | AF19: ৩০ নভেম্বর | AG19: =W19 -> 45991 | AH19: ৩০ জুন | AI19: =AG19+212 -> 46203 | AJ19: =$M$34 -> 724431.84 | AK19: =$L$42 -> 0 | AL19: No | AM19: =U19+(365*2) -> 46569 | AN19: 2 | AO19: =$L$32 -> 739000 | AP19: 2000000 | AQ19: =MIN('Sheet of Calculation'!C35:D35)*'Sheet of Calculation'!E35 -> 500000 | AR19: =MIN('MisC Cal-1'!C15:D15)*'MisC Cal-1'!E15 -> 500000
R20: 2026-27 | S20: =U19 -> 45839 | T20: =S20+364 -> 46203 | U20: =T20+1 -> 46204 | V20: =U20+364 -> 46568 | W20: =U20+152 -> 46356 | X20: =$S$7 -> 0.02 | Y20: =$Y$8 -> 0 | Z20: 375000 | AA20: 300000 | AB20: 0.1 | AC20: 400000 | AD20: 500000 | AE20: 2000000 | AF20: ৩০ নভেম্বর | AG20: =W20 -> 46356 | AH20: ৩০ জুন | AI20: =AG20+212 -> 46568 | AJ20: =$M$34 -> 724431.84 | AK20: =$L$42 -> 0 | AL20: No | AM20: =U20+(365*2)+1 -> 46935 | AN20: 2 | AO20: =$L$32 -> 739000 | AP20: Aewkó | AQ20: =('Sheet of Calculation'!$C$35)*('Sheet of Calculation'!$E$35) -> 903088.75 | AR20: =('MisC Cal-1'!$C$15)*('MisC Cal-1'!$E$15) -> 1335124.2
K21: Assessment Date = | L21: ='Data Input'!F5 -> 46386 | R21: 2027-28 | S21: =U20 -> 46204 | T21: =S21+364 -> 46568 | U21: =T21+1 -> 46569 | V21: =U21+364 -> 46933 | W21: =U21+152 -> 46721 | X21: =$S$7 -> 0.02 | Y21: =$Y$8 -> 0 | Z21: 375000 | AA21: 300000 | AB21: 0.1 | AC21: 400000 | AD21: 500000 | AE21: 2000000 | AF21: ৩০ নভেম্বর | AG21: =W21 -> 46721 | AH21: ৩০ জুন | AI21: =AG21+213 -> 46934 | AJ21: =$M$34 -> 724431.84 | AK21: =$L$42 -> 0 | AL21: No | AM21: =U21+(365*2)+1 -> 47300 | AN21: 2 | AO21: =$L$32 -> 739000 | AP21: Aewkó | AQ21: =('Sheet of Calculation'!$C$35)*('Sheet of Calculation'!$E$35) -> 903088.75 | AR21: =('MisC Cal-1'!$C$15)*('MisC Cal-1'!$E$15) -> 1335124.2
R22: 2028-29 | S22: =U21 -> 46569 | T22: =S22+365 -> 46934 | U22: =T22+1 -> 46935 | V22: =U22+364 -> 47299 | W22: =U22+152 -> 47087 | X22: =$S$7 -> 0.02 | Y22: =$Y$8 -> 0 | Z22: 375000 | AA22: 300000 | AB22: 0.1 | AC22: 400000 | AD22: 500000 | AE22: 2000000 | AF22: ৩০ নভেম্বর | AG22: =W22 -> 47087 | AH22: ৩০ জুন | AI22: =AG22+212 -> 47299 | AJ22: =$M$34 -> 724431.84 | AK22: =$L$42 -> 0 | AL22: No | AM22: =U22+(365*2) -> 47665 | AN22: 2 | AO22: =$L$32 -> 739000 | AP22: Aewkó | AQ22: =('Sheet of Calculation'!$C$35)*('Sheet of Calculation'!$E$35) -> 903088.75 | AR22: =('MisC Cal-1'!$C$15)*('MisC Cal-1'!$E$15) -> 1335124.2
R23: 2029-30 | S23: =U22 -> 46935 | T23: =S23+364 -> 47299 | U23: =T23+1 -> 47300 | V23: =U23+364 -> 47664 | W23: =U23+152 -> 47452 | X23: =$S$7 -> 0.02 | Y23: =$Y$8 -> 0 | Z23: 375000 | AA23: 300000 | AB23: 0.1 | AC23: 400000 | AD23: 500000 | AE23: 2000000 | AF23: ৩০ নভেম্বর | AG23: =W23 -> 47452 | AH23: ৩০ জুন | AI23: =AG23+212 -> 47664 | AJ23: =$M$34 -> 724431.84 | AK23: =$L$42 -> 0 | AL23: No | AM23: =U23+(365*2) -> 48030 | AN23: 2 | AO23: =$L$32 -> 739000 | AP23: Aewkó | AQ23: =('Sheet of Calculation'!$C$35)*('Sheet of Calculation'!$E$35) -> 903088.75 | AR23: =('MisC Cal-1'!$C$15)*('MisC Cal-1'!$E$15) -> 1335124.2
K24: Assessment Current Year = | L24: =IF(AND(L21>=U14,L21<=V14),R14,IF(AND(L21>=U15,L21<=V15),R15,IF(AND(L21>=U16,L21<=V16),R16,IF(AND(L21>=U17,L21<=V17),R17,IF(AND(L21>=U18,L21<=V18),R18,IF(AND(L21>=U19,L21<=V19),R19,0)))))) -> 0
K26: Desk Audit Hearing | L26: =L5+'Data Input'!I51 -> 46408
K27: Demand Notice Date | L27: =L5+'Data Input'!K51 -> 46413
K30: Delay Interest rate | L30: =_xlfn.XLOOKUP(L3,R10:R23,X10:X23,0) -> 0.02 | M30: u/s 44(5)(a) or, 174 | N30: ='Data Input'!D9 -> স্বনির্ধারণী | O30: =_xlfn.XLOOKUP(N30,N32:N34,P32:P34,0) -> 45991 | Q30: Delay Interest (Round ) | S30: ='MisC Intrst-3'!L43 -> 0
K31: Tax Assessed | L31: ='Sheet of Calculation'!F44 -> 1463431.8 | M31: ='Sheet of Calculation'!F44+'Sheet of Calculation'!F47 -> 1517267 | N31: Tax Day | O31: =_xlfn.XLOOKUP(N30,N32:N34,O32:O34,0) -> ৩০ নভেম্বর | R31: ="( wej¤^ my` = "&'MisC Intrst-3'!L43&"/- UvKv ) BZ¨vw` " -> ( wej¤^ my` = 0/- UvKv ) BZ¨vw` | T31: 174 avivbymv‡i
K32: Tax Paid in Advance (All) | L32: ='Sheet of Calculation'!C47+'Sheet of Calculation'!C48+'Sheet of Calculation'!C49 -> 739000 | M32: =_xlfn.XLOOKUP(L3,R10:R23,AO10:AO23,0) -> 739000 | N32: স্বনির্ধারণী | O32: =_xlfn.XLOOKUP(L3,R10:R23,AF10:AF23,0) -> ৩০ নভেম্বর | P32: =_xlfn.XLOOKUP(L3,R10:R23,AG10:AG23,0) -> 45991 | R32: =IF(S30>0,R31,T30) | T32: =IF(M37=M33,T31,T30)
K33: Difference | L33: =L31-L32 -> 724431.84 | M33: =M31-M32 -> 778267.04 | N33: নতুন করদাতা | O33: =_xlfn.XLOOKUP(L3,R10:R23,AH10:AH23,0) -> ৩০ জুন | P33: =_xlfn.XLOOKUP(L3,R10:R23,AI10:AI23,0) -> 46203
K34: Actual Tax Day | L34: =O30 -> 45991 | M34: =IF(O41>0,M33,L33) -> 724431.84 | N34: সাধারণ (বিলম্ব সুদ) | O34: =_xlfn.XLOOKUP(L3,R10:R23,AF10:AF23,0) -> ৩০ নভেম্বর | P34: =_xlfn.XLOOKUP(L3,R10:R23,AG10:AG23,0) -> 45991
K35: Return Submission | L35: ='Data Input'!D5 -> 45962 | M35: Actual/Round Fig (Months) | N35: Assumed Tax Date: | O35: =_xlfn.XLOOKUP(L3,R10:R23,W10:W23,0) -> 45991
K36: Interval Months | L36: =MIN(IF(((L35-L34)/30)<0,0,((L35-L34)/30)),12) -> 0 | M36: =_xlfn.XLOOKUP(L3,R10:R23,Y10:Y23,0) -> 0 | N36: Actual Tax Day | O36: =O30 -> 45991
K37: Delay Interest | L37: =M37*L30*M36 -> 0 | M37: =_xlfn.XLOOKUP(L3,R10:R23,AJ10:AJ23,0) -> 724431.84 | N37: Normal Return Last Day | O37: =O35+120 -> 46111
K38: Delay Interest (Round ) | L38: =ROUND(L37,0) -> 0 | Q38: Return Submission | R38: ='Data Input'!D5 -> 45962
K39: Delay Int (>= 0) | L39: =IF(L38>0,L38,0) -> 0 | N39: Actual Tax Day | O39: =O30 -> 45991 | Q39: Income Tax Act, 2023 Enacts | R39: =DATE(2023,7,1) -> 45108
K40: Submission/Assessment Date Unreal | N40: Return Submission | O40: ='Data Input'!D5 -> 45962 | Q40: Difference(174 Tax) | R40: =R38-R39 -> 854
K41: =IF((L4-N6)<0,0,L39) -> 0 | L41: =IF((L5-L4)<0,0,K41) -> 0 | N41: Difference | O41: =O40-O39 -> -29 | R41: ='MisC Cal-2'!H82 -> 0
K42: Real Delay Int. | L42: =L41 -> 0
K43: Final Delay Int. | L43: =_xlfn.XLOOKUP(L3,R10:R23,AK10:AK23,0) -> 0

Sheet Balance sheet
B6: =#REF! -> #REF!
B7: =#REF! -> #REF!
B8: =#REF! -> #REF!
B9: =#REF! -> #REF!
B10: Assessment Year -2013-2014
C12: Statement of Accounts for the year ended 30-06-2013
B14: Business: Dealing Accessories supply
C16: Trading Accounts for the year ended 30-06-2013
B18: To | C18: Opening Stock | D18: Tk. | E18: 0 | F18: By | G18: Sales | H18: Tk. | I18: =E20*100/15 -> 12080000
B19: To | C19: Purchase | D19: Tk. | E19: =E21-E18-E20 -> 10268000 | F19: By | G19: Closing Stock | H19: Tk. | I19: 0
B20: To | C20: Gross Profit | D20: Tk. | E20: =I25 -> 1812000
E21: =I21 -> 12080000 | I21: =SUM(I18:I20) -> 12080000
C23: Profi & Loss Accounts for the year ended 30-06-2013
B25: To | C25: Business Exp. | D25: Tk. | E25: =E26/2 -> 604000 | F25: By | G25: Gross Profit | H25: Tk. | I25: =E25*3 -> 1812000
B26: To | C26: Net Profit 82 C | D26: Tk. | E26: 1208000
E29: =E25+E26 -> 1812000 | I29: =E29 -> 1812000
B32: Balance Sheet for the year ended 30-06-2013
C33: Capital & Liabilities | G33: Property & Assets
C34: Capital | D34: Tk. | E34: 158500 | G34: Closing stock | H34: Tk. | I34: 0
C35: Add.Net Profit | D35: Tk. | E35: =E26 -> 1208000 | G35: Sundry Assets | H35: Tk. | I35: 10000
E36: =SUM(E34:E35) -> 1366500 | G36: Cash in Hand & Bank | H36: Tk | I36: =+I38-I34-I35 -> 481500
C37: Less. Famely Exp | D37: Tk. | E37: 875000
E38: =E36-E37 -> 491500 | I38: =E38 -> 491500
